learn/half_add/Half_Add.v
module Half_Add(A,B,O,C);

    /*采用连续赋值的方式实现半加器*/
    input wire A,B;
    output wire O,C;
    assign O = A^B;     //assign 赋值时只能是wire类型   ^是异或 运算符
    assign C = A&B;
    // assign {C,O}    = A+B;  //{}是位拼接运算符 半加器的另一种实现方法

    /*采用always块实现半加器*/
    // input wire A,B;
    // output reg O,C;
    // always@(*) begin
    //     {C,O} = A+B;
    // end

endmodule

learn/half_add/Full_Add.v
`include "Half_Add.v"
//使用两个半加器实现全加器
module Full_Add(num1,num2,cin,sum,cout);

    input wire num1,num2,cin;      // 加数 被加数 上一个进位   input 后面不能跟reg
    output wire sum,cout;     // 和 进位


    wire sum1,cin1,cout1,cout2;

    Half_Add HA1(num1,num2,sum1,cout1);
    Half_Add HA2(sum1,cin,sum,cout2);

    assign cout = cout1 | cout2;

endmodule

learn/half_add/Full_Add_tb.v
`timescale 10ns/1ns
// `include "Full_Add.v"
module Full_Add_tb();
    reg a,b,cin;
    wire sum,cout;
    Full_Add uut(a,b,cin,sum,cout);

    initial begin
        $dumpfile("Full_Add.vcd");
        $dumpvars(0,Full_Add_tb);
    end

    initial begin
        a=0;b=0;cin=0;
        #10 a=0;b=0;cin=1;
        #10 a=0;b=1;cin=0;
        #10 a=0;b=1;cin=1;
        #10 a=1;b=0;cin=0;
        #10 a=1;b=0;cin=1;
        #10 a=1;b=1;cin=0;
        #10 a=1;b=1;cin=1;
        #10 $finish;
    end
endmodule

learn/half_add/Full_Add.vcd
$date
	Wed Aug 12 11:44:21 2026
$end
$version
	Icarus Verilog
$end
$timescale
	1ns
$end
$scope module Full_Add_tb $end
$var wire 1 ! sum $end
$var wire 1 " cout $end
$var reg 1 # a $end
$var reg 1 $ b $end
$var reg 1 % cin $end
$scope module uut $end
$var wire 1 % cin $end
$var wire 1 " cout $end
$var wire 1 # num1 $end
$var wire 1 $ num2 $end
$var wire 1 & sum1 $end
$var wire 1 ! sum $end
$var wire 1 ' cout2 $end
$var wire 1 ( cout1 $end
$scope module HA1 $end
$var wire 1 # A $end
$var wire 1 $ B $end
$var wire 1 ( C $end
$var wire 1 & O $end
$upscope $end
$scope module HA2 $end
$var wire 1 & A $end
$var wire 1 % B $end
$var wire 1 ' C $end
$var wire 1 ! O $end
$upscope $end
$upscope $end
$upscope $end
$enddefinitions $end
$comment Show the parameter values. $end
$dumpall
$end
#0
$dumpvars
0(
0'
0&
0%
0$
0#
0"
0!
$end
#100
1!
1%
#200
1&
0%
1$
#300
1"
0!
1'
1%
#400
0"
1!
0'
0%
0$
1#
#500
1"
0!
1'
1%
#600
0'
0&
1(
0%
1$
#700
1!
1%
