learn/FIFO/sync_fifo.v
module sync_fifo
#(
    parameter DATA_WIDTH = 8,    // 单个数据位宽
    parameter DEPTH      = 8     // FIFO深度，建议2的幂次
)
(
    input  wire                     clk,
    input  wire                     rst_n,      // 异步低电平复位
    // 写端口
    input  wire                     wr_en,      // 写使能，高有效
    input  wire [DATA_WIDTH-1:0]    din,        // 写入数据
    // 读端口
    input  wire                     rd_en,      // 读使能，高有效
    output reg  [DATA_WIDTH-1:0]    dout,       // 读出数据
    // 状态标志
    output reg                      empty,      // 空标志：1=无数据不可读
    output reg                      full        // 满标志：1=空间已满不可写
);

// 计算指针位宽：地址位宽 + 1位冗余位
localparam ADDR_BIT = $clog2(DEPTH);
localparam PTR_WID  = ADDR_BIT + 1;

// 读写指针
reg [PTR_WID-1:0] wr_ptr;
reg [PTR_WID-1:0] rd_ptr;

// FIFO存储数组
reg [DATA_WIDTH-1:0] fifo_mem [0:DEPTH-1];

// ====================== 1. 写指针逻辑 ======================
always @(posedge clk or negedge rst_n) begin
    if (!rst_n) begin
        wr_ptr <= {PTR_WID{1'b0}};
    end
    else if (wr_en && !full) begin
        wr_ptr <= wr_ptr + 1'b1;
    end
end

// ====================== 2. 读指针逻辑 ======================
always @(posedge clk or negedge rst_n) begin
    if (!rst_n) begin
        rd_ptr <= {PTR_WID{1'b0}};
    end
    else if (rd_en && !empty) begin
        rd_ptr <= rd_ptr + 1'b1;
    end
end

// ====================== 3. 写入存储器 ======================
always @(posedge clk) begin
    if (wr_en && !full) begin
        fifo_mem[wr_ptr[ADDR_BIT-1:0]] <= din;  //取wr_ptr的低ADDR_BIT位作为地址 高位作为满标志
    end
end

// ====================== 4. 读出数据 ======================
always @(posedge clk or negedge rst_n) begin
    if (!rst_n) begin
        dout <= {DATA_WIDTH{1'b0}};
    end
    else if (rd_en && !empty) begin
        dout <= fifo_mem[rd_ptr[ADDR_BIT-1:0]]; // 取rd_ptr的低ADDR_BIT位作为地址 
    end
end

// ====================== 5. 空、满判断（组合逻辑） ======================
always @(*) begin
    // 空：读写指针完全相等
    empty = (wr_ptr == rd_ptr);
    // 满：最高位相反，低位地址完全相同
    full  = (wr_ptr[PTR_WID-1] != rd_ptr[PTR_WID-1])
         && (wr_ptr[ADDR_BIT-1:0] == rd_ptr[ADDR_BIT-1:0]);
end

endmodule

learn/FIFO/sync_fifo_tb.v
`include "sync_fifo.v"
module sync_fifo_tb;

parameter DW = 8;
parameter DP = 8;

reg                     clk;
reg                     rst_n;
reg                     wr_en;
reg [DW-1:0]            din;
reg                     rd_en;
wire [DW-1:0]           dout;
wire                    empty;
wire                    full;

// 例化FIFO
sync_fifo #(
    .DATA_WIDTH(DW),
    .DEPTH(DP)
) u_sync_fifo (.*);

// 生成系统时钟 100MHz 周期10ns
initial begin
    clk = 1'b0;
    forever #5 clk = ~clk;
end

// 测试激励
initial begin
    rst_n  = 1'b0;
    wr_en  = 1'b0;
    rd_en  = 1'b0;
    din    = 8'd0;
    #10 rst_n = 1'b1;

    // 阶段1：连续写入8个数据，写满FIFO
    repeat(8) begin
        @(posedge clk);
        wr_en = 1'b1;
        din   = din + 1'b1;
    end
    @(posedge clk);
    wr_en = 1'b0;

    #20;

    // 阶段2：连续读出所有数据
    repeat(8) begin
        @(posedge clk);
        rd_en = 1'b1;
    end
    @(posedge clk);
    rd_en = 1'b0;

    #50;
    $finish;
end

// 导出波形文件
initial begin
    $dumpfile("sync_fifo.vcd");
    $dumpvars(0, sync_fifo_tb);
end

endmodule

learn/FIFO/sync_fifo.vcd
$date
	Fri Aug 14 10:38:36 2026
$end
$version
	Icarus Verilog
$end
$timescale
	1s
$end
$scope module sync_fifo_tb $end
$var wire 1 ! full $end
$var wire 1 " empty $end
$var wire 8 # dout [7:0] $end
$var parameter 32 $ DP $end
$var parameter 32 % DW $end
$var reg 1 & clk $end
$var reg 8 ' din [7:0] $end
$var reg 1 ( rd_en $end
$var reg 1 ) rst_n $end
$var reg 1 * wr_en $end
$scope module u_sync_fifo $end
$var wire 1 & clk $end
$var wire 8 + din [7:0] $end
$var wire 1 ( rd_en $end
$var wire 1 ) rst_n $end
$var wire 1 * wr_en $end
$var parameter 32 , ADDR_BIT $end
$var parameter 32 - DATA_WIDTH $end
$var parameter 32 . DEPTH $end
$var parameter 33 / PTR_WID $end
$var reg 8 0 dout [7:0] $end
$var reg 1 " empty $end
$var reg 1 ! full $end
$var reg 4 1 rd_ptr [3:0] $end
$var reg 4 2 wr_ptr [3:0] $end
$upscope $end
$upscope $end
$enddefinitions $end
$comment Show the parameter values. $end
$dumpall
b100 /
b1000 .
b1000 -
b11 ,
b1000 %
b1000 $
$end
#0
$dumpvars
b0 2
b0 1
b0 0
b0 +
0*
0)
0(
b0 '
0&
b0 #
1"
0!
$end
#5
1&
#10
0&
1)
#15
0"
b1 2
b1 '
b1 +
1*
1&
#20
0&
#25
b10 2
b10 '
b10 +
1&
#30
0&
#35
b11 2
b11 '
b11 +
1&
#40
0&
#45
b100 2
b100 '
b100 +
1&
#50
0&
#55
b101 2
b101 '
b101 +
1&
#60
0&
#65
b110 2
b110 '
b110 +
1&
#70
0&
#75
b111 2
b111 '
b111 +
1&
#80
0&
#85
1!
b1000 2
b1000 '
b1000 +
1&
#90
0&
#95
0*
1&
#100
0&
#105
1&
#110
0&
#115
0!
b1 1
b1 #
b1 0
1(
1&
#120
0&
#125
b10 1
1&
#130
0&
#135
b11 1
b11 #
b11 0
1&
#140
0&
#145
b100 1
1&
#150
0&
#155
b101 1
b101 #
b101 0
1&
#160
0&
#165
b110 1
1&
#170
0&
#175
b111 1
b111 #
b111 0
1&
#180
0&
#185
1"
b1000 1
1&
#190
0&
#195
0(
1&
