learn/Counter1/Counter1.v
module Counter1(
    input clk,
    input rstn,
    output reg [4:0] onesPlace,
    output reg [4:0] tensPlace,
    output reg [4:0] hundredsPlace,
    output reg en
);

always @(posedge clk or negedge rstn) begin
    if(rstn == 0) begin
        onesPlace <= 0;
    end
    else if(onesPlace == 9) begin
        onesPlace <=0;
    end
    else
        onesPlace <= onesPlace + 1;
end

always @(posedge clk or negedge rstn) begin
     if(rstn == 0)begin
        tensPlace <= 0;
    end
    else if(onesPlace == 4'd9) begin
        tensPlace <= 0;
        tensPlace <= tensPlace + 1;
    end
    else 
        tensPlace <= tensPlace;
end
always @(posedge clk or negedge rstn) begin
     if(rstn == 0)begin
        hundredsPlace <= 0;
    end
    else if(tensPlace == 4'd9 && onesPlace == 4'd9)
        hundredsPlace <= hundredsPlace +1'b1;
    else 
       hundredsPlace <= hundredsPlace;
end
always @(posedge clk or negedge rstn) begin
     if(rstn == 0)begin
        en <= 0;
    end
    else if(tensPlace == 4'd9 && onesPlace == 4'd9 && hundredsPlace == 4'd9) begin
        hundredsPlace <= 0;
        en <= 1;
    end
    else 
       en <= en;
end


endmodule

learn/Counter1/Counter1_tb.v
`timescale 1ns/1ns
// `include "Counter1.v"
module Counter1_tb();
    reg clk;
    reg rstn;
    wire [4:0] onesPlace;
    wire [4:0] tensPlace;
    wire [4:0] hundredsPlace;
    wire en;

Counter1 dut(clk,rstn,onesPlace,tensPlace,hundredsPlace,en);
always #1 clk <=~clk;
initial begin
    $dumpfile("wave.vcd");
    $dumpvars(0,Counter1_tb);
end
initial begin
    clk = 0;
    rstn = 0;
    #10 
    rstn = 1;

    # 110
    $finish;
end




endmodule

learn/Counter1/wave.vcd
$date
	Thu Aug 27 21:54:50 2026
$end
$version
	Icarus Verilog
$end
$timescale
	1ns
$end
$scope module Counter1_tb $end
$var wire 5 ! tensPlace [4:0] $end
$var wire 5 " onesPlace [4:0] $end
$var wire 5 # hundredsPlace [4:0] $end
$var wire 1 $ en $end
$var reg 1 % clk $end
$var reg 1 & rstn $end
$scope module dut $end
$var wire 1 % clk $end
$var wire 1 & rstn $end
$var reg 1 $ en $end
$var reg 5 ' hundredsPlace [4:0] $end
$var reg 5 ( onesPlace [4:0] $end
$var reg 5 ) tensPlace [4:0] $end
$upscope $end
$upscope $end
$enddefinitions $end
$comment Show the parameter values. $end
$dumpall
$end
#0
$dumpvars
b0 )
b0 (
b0 '
0&
0%
0$
b0 #
b0 "
b0 !
$end
#1
1%
#2
0%
#3
1%
#4
0%
#5
1%
#6
0%
#7
1%
#8
0%
#9
1%
#10
0%
1&
#11
b1 "
b1 (
1%
#12
0%
#13
b10 "
b10 (
1%
#14
0%
#15
b11 "
b11 (
1%
#16
0%
#17
b100 "
b100 (
1%
#18
0%
#19
b101 "
b101 (
1%
#20
0%
#21
b110 "
b110 (
1%
#22
0%
#23
b111 "
b111 (
1%
#24
0%
#25
b1000 "
b1000 (
1%
#26
0%
#27
b1001 "
b1001 (
1%
#28
0%
#29
b1 !
b1 )
b0 "
b0 (
1%
#30
0%
#31
b1 "
b1 (
1%
#32
0%
#33
b10 "
b10 (
1%
#34
0%
#35
b11 "
b11 (
1%
#36
0%
#37
b100 "
b100 (
1%
#38
0%
#39
b101 "
b101 (
1%
#40
0%
#41
b110 "
b110 (
1%
#42
0%
#43
b111 "
b111 (
1%
#44
0%
#45
b1000 "
b1000 (
1%
#46
0%
#47
b1001 "
b1001 (
1%
#48
0%
#49
b10 !
b10 )
b0 "
b0 (
1%
#50
0%
#51
b1 "
b1 (
1%
#52
0%
#53
b10 "
b10 (
1%
#54
0%
#55
b11 "
b11 (
1%
#56
0%
#57
b100 "
b100 (
1%
#58
0%
#59
b101 "
b101 (
1%
#60
0%
#61
b110 "
b110 (
1%
#62
0%
#63
b111 "
b111 (
1%
#64
0%
#65
b1000 "
b1000 (
1%
#66
0%
#67
b1001 "
b1001 (
1%
#68
0%
#69
b11 !
b11 )
b0 "
b0 (
1%
#70
0%
#71
b1 "
b1 (
1%
#72
0%
#73
b10 "
b10 (
1%
#74
0%
#75
b11 "
b11 (
1%
#76
0%
#77
b100 "
b100 (
1%
#78
0%
#79
b101 "
b101 (
1%
#80
0%
#81
b110 "
b110 (
1%
#82
0%
#83
b111 "
b111 (
1%
#84
0%
#85
b1000 "
b1000 (
1%
#86
0%
#87
b1001 "
b1001 (
1%
#88
0%
#89
b100 !
b100 )
b0 "
b0 (
1%
#90
0%
#91
b1 "
b1 (
1%
#92
0%
#93
b10 "
b10 (
1%
#94
0%
#95
b11 "
b11 (
1%
#96
0%
#97
b100 "
b100 (
1%
#98
0%
#99
b101 "
b101 (
1%
#100
0%
#101
b110 "
b110 (
1%
#102
0%
#103
b111 "
b111 (
1%
#104
0%
#105
b1000 "
b1000 (
1%
#106
0%
#107
b1001 "
b1001 (
1%
#108
0%
#109
b101 !
b101 )
b0 "
b0 (
1%
#110
0%
#111
b1 "
b1 (
1%
#112
0%
#113
b10 "
b10 (
1%
#114
0%
#115
b11 "
b11 (
1%
#116
0%
#117
b100 "
b100 (
1%
#118
0%
#119
b101 "
b101 (
1%
