learn/Counter/Cnt_1s.v
module Cnt_1s(clk,rst,counter,led);
input clk,rst;
output reg [25:0] counter;
output reg led;
always @(posedge clk) begin
    if(rst == 1) begin
        counter <= 0;
         led <= 0;
    end
    else if(counter == 49_999_999) begin  // 1s = 50M/50 = 1M
        counter <= 0;
        led <= ~led;
    end
    else
        counter <= counter + 1;
end

endmodule

learn/Counter/Cnt_1s_tb.v
`timescale  1ns/1ns
module Cnt_1s_tb;
reg clk;
reg rst;
wire [25:0] cnt;
wire led;
Cnt_1s dut(clk, rst, cnt,led);
initial begin
    $dumpfile("Cnt_1s.vcd");
    $dumpvars(0, Cnt_1s_tb);
end
initial begin
    clk = 0;
    rst = 1;
    
end

initial begin
    #10
    rst = 0;
    # 100
    $finish;
end
always #1 clk = ~clk;
endmodule

learn/Counter/Cnt_1s.vcd
$date
	Wed Aug 12 17:21:37 2026
$end
$version
	Icarus Verilog
$end
$timescale
	1ns
$end
$scope module Cnt_1s_tb $end
$var wire 1 ! led $end
$var wire 26 " cnt [25:0] $end
$var reg 1 # clk $end
$var reg 1 $ rst $end
$scope module dut $end
$var wire 1 # clk $end
$var wire 1 $ rst $end
$var reg 26 % counter [25:0] $end
$var reg 1 ! led $end
$upscope $end
$upscope $end
$enddefinitions $end
$comment Show the parameter values. $end
$dumpall
$end
#0
$dumpvars
bx %
1$
0#
bx "
x!
$end
#1
0!
b0 "
b0 %
1#
#2
0#
#3
1#
#4
0#
#5
1#
#6
0#
#7
1#
#8
0#
#9
1#
#10
0#
0$
#11
b1 "
b1 %
1#
#12
0#
#13
b10 "
b10 %
1#
#14
0#
#15
b11 "
b11 %
1#
#16
0#
#17
b100 "
b100 %
1#
#18
0#
#19
b101 "
b101 %
1#
#20
0#
#21
b110 "
b110 %
1#
#22
0#
#23
b111 "
b111 %
1#
#24
0#
#25
b1000 "
b1000 %
1#
#26
0#
#27
b1001 "
b1001 %
1#
#28
0#
#29
1!
b0 "
b0 %
1#
#30
0#
#31
b1 "
b1 %
1#
#32
0#
#33
b10 "
b10 %
1#
#34
0#
#35
b11 "
b11 %
1#
#36
0#
#37
b100 "
b100 %
1#
#38
0#
#39
b101 "
b101 %
1#
#40
0#
#41
b110 "
b110 %
1#
#42
0#
#43
b111 "
b111 %
1#
#44
0#
#45
b1000 "
b1000 %
1#
#46
0#
#47
b1001 "
b1001 %
1#
#48
0#
#49
0!
b0 "
b0 %
1#
#50
0#
#51
b1 "
b1 %
1#
#52
0#
#53
b10 "
b10 %
1#
#54
0#
#55
b11 "
b11 %
1#
#56
0#
#57
b100 "
b100 %
1#
#58
0#
#59
b101 "
b101 %
1#
#60
0#
#61
b110 "
b110 %
1#
#62
0#
#63
b111 "
b111 %
1#
#64
0#
#65
b1000 "
b1000 %
1#
#66
0#
#67
b1001 "
b1001 %
1#
#68
0#
#69
1!
b0 "
b0 %
1#
#70
0#
#71
b1 "
b1 %
1#
#72
0#
#73
b10 "
b10 %
1#
#74
0#
#75
b11 "
b11 %
1#
#76
0#
#77
b100 "
b100 %
1#
#78
0#
#79
b101 "
b101 %
1#
#80
0#
#81
b110 "
b110 %
1#
#82
0#
#83
b111 "
b111 %
1#
#84
0#
#85
b1000 "
b1000 %
1#
#86
0#
#87
b1001 "
b1001 %
1#
#88
0#
#89
0!
b0 "
b0 %
1#
#90
0#
#91
b1 "
b1 %
1#
#92
0#
#93
b10 "
b10 %
1#
#94
0#
#95
b11 "
b11 %
1#
#96
0#
#97
b100 "
b100 %
1#
#98
0#
#99
b101 "
b101 %
1#
#100
0#
#101
b110 "
b110 %
1#
#102
0#
#103
b111 "
b111 %
1#
#104
0#
#105
b1000 "
b1000 %
1#
#106
0#
#107
b1001 "
b1001 %
1#
#108
0#
#109
1!
b0 "
b0 %
1#
