learn/3to8Decoder/Three_To_Eight_Decoder.v
module Three_To_Eight_Decoder(in,out);

input wire [2:0] in;
output reg [7:0] out;

always@(*) begin
	case(in)
		3'b000: out = 8'b0000_0000;
		3'b001: out = 8'b0000_0001;
		3'b010: out = 8'b0000_0010;
		3'b011: out = 8'b0000_0100;
		3'b100: out = 8'b0000_1000;
		3'b101: out = 8'b0001_0000;
		3'b110: out = 8'b0010_0000;
		3'b111: out = 8'b0100_0000;
	endcase
end


endmodule

learn/3to8Decoder/Three_To_Eight_Decoder_tb.v
`timescale 10ns/10ns
// `include "Three_To_Eight_Decoder.v"
module Three_To_Eight_Decoder_tb();

reg [2:0] a;
wire [7:0] y;
Three_To_Eight_Decoder dut(a,y);
initial begin
    $dumpfile("Three_To_Eight_Decoder.vcd");
    $dumpvars(0, Three_To_Eight_Decoder_tb);
end
initial begin
    a=3'b000;
    #10 a=3'b001;
    #10 a=3'b010;
    #10 a=3'b011;
    #10 a=3'b100;
    #10 a=3'b101;
    #10 a=3'b110;
    #10 a=3'b111;
    #10 $finish;
end
endmodule

learn/3to8Decoder/Three_To_Eight_Decoder.vcd
$date
	Wed Aug 12 10:37:03 2026
$end
$version
	Icarus Verilog
$end
$timescale
	10ns
$end
$scope module Three_To_Eight_Decoder_tb $end
$var wire 8 ! y [7:0] $end
$var reg 3 " a [2:0] $end
$scope module dut $end
$var wire 3 # in [2:0] $end
$var reg 8 $ out [7:0] $end
$upscope $end
$upscope $end
$enddefinitions $end
$comment Show the parameter values. $end
$dumpall
$end
#0
$dumpvars
b0 $
b0 #
b0 "
b0 !
$end
#10
b1 !
b1 $
b1 "
b1 #
#20
b10 !
b10 $
b10 "
b10 #
#30
b100 !
b100 $
b11 "
b11 #
#40
b1000 !
b1000 $
b100 "
b100 #
#50
b10000 !
b10000 $
b101 "
b101 #
#60
b100000 !
b100000 $
b110 "
b110 #
#70
b1000000 !
b1000000 $
b111 "
b111 #
