learn/UART/uart_sender.v
module uart_sender(clk,reset,tx_data,en_sig,tx_done,tx);
   input clk;
   input reset;
   input en_sig;
   input [9:0] tx_data;         // 10bit 数据包含其实和停止位
   output reg tx_done;
   output reg tx;

   parameter baudrate = 9600;       // baudrate
   parameter clk_freq = 50_000_000; // 50MHz
   parameter clk_div = clk_freq/baudrate; // 时钟分频



    reg [3:0] current_state;
    reg [3:0] next_state;
    parameter IDLE = 4'b0001;
    parameter START = 4'b0010;
    parameter STOP = 4'b1000;
    //状态机 状态传递 部分
    always@(posedge clk or negedge reset) begin
        if(reset == 0) begin
            current_state <= IDLE;
        end
        else begin
            current_state <= next_state;
        end
    end
    //状态机 状态切换 部分
    always@(*) begin
        case(current_state)
            IDLE: begin
                if(en_sig == 1'b1) begin
                    next_state = START;
                end
                else begin
                    next_state = IDLE;
                end
            end
            START: begin
                if(bit_cnt == 4'b1010) begin
                    next_state = STOP;
                end
                else begin
                    next_state = START;
                end
            end
            STOP: begin
                next_state = IDLE;
            end
        endcase
    end
    // 状态机 状态输出 部分
    always@(posedge clk or negedge reset) begin
        if(reset == 0) begin
            tx_done <= 1'b0;
        end
        case(current_state)
            IDLE: begin
                tx_done <= 1'b0;
            end
            START: begin
                tx_done <= 1'b0;
                tx <= tx_data[9-bit_cnt];
            end
            STOP: begin
                tx_done <= 1'b1;
            end
        endcase
    end


    reg [12:0] div_cnt;
    //分频计数器
    always@(posedge clk or negedge reset) begin
        if(reset == 0)begin
          div_cnt <= 13'b0;
        end
        else if(current_state == START) begin
            if(div_cnt == clk_div)begin
                div_cnt <= 13'b0;
            end
            else begin
                div_cnt <= div_cnt + 1'b1;
            end
        end
        else 
            div_cnt <= 13'b0;
    end


    reg [3:0] bit_cnt;
    //数据位计数器
    always@(posedge clk or negedge reset) begin
        if(reset == 0)begin
          bit_cnt <= 4'b0;
        end
        else if(current_state == START ) begin
            if(div_cnt == clk_div)begin
                if(bit_cnt == 4'b1010) begin
                    bit_cnt <= 4'b0;
                end
                else begin
                    bit_cnt <= bit_cnt + 1'b1;
                end
            end
        end
        else 
            bit_cnt <= 4'b0;
    end
endmodule

learn/UART/uart_sender_tb.v
`timescale 1ns/1ns
module uart_sender_tb;
reg clk;
reg rst;
reg [9:0] data;
reg enable;
wire tx_done;
wire tx;
uart_sender dut(

	.clk(clk),
	.reset(rst),
	.tx_data(data),
	.en_sig(enable),
    .tx_done(tx_done),
	.tx(tx)
);
initial begin

	$dumpfile("uart_sender_tb.vcd");
	$dumpvars(0, uart_sender_tb);
end



initial begin
	clk = 0;
	rst = 0;
	data = 10'b0101010100;
	enable = 0;
    # 10 rst = 1;
    # 10 enable = 1;
    # 1000000  
    $finish;
end
always #5 clk = ~clk;

endmodule

learn/UART/uart_sender_tb.vcd
$date
	Wed Aug 19 15:38:32 2026
$end
$version
	Icarus Verilog
$end
$timescale
	1ns
$end
$scope module uart_sender_tb $end
$var wire 1 ! tx_done $end
$var wire 1 " tx $end
$var reg 1 # clk $end
$var reg 10 $ data [9:0] $end
$var reg 1 % enable $end
$var reg 1 & rst $end
$scope module dut $end
$var wire 1 # clk $end
$var wire 1 % en_sig $end
$var wire 1 & reset $end
$var wire 10 ' tx_data [9:0] $end
$var parameter 4 ( IDLE $end
$var parameter 4 ) START $end
$var parameter 4 * STOP $end
$var parameter 32 + baudrate $end
$var parameter 32 , clk_div $end
$var parameter 32 - clk_freq $end
$var reg 4 . bit_cnt [3:0] $end
$var reg 4 / current_state [3:0] $end
$var reg 13 0 div_cnt [12:0] $end
$var reg 4 1 next_state [3:0] $end
$var reg 1 " tx $end
$var reg 1 ! tx_done $end
$upscope $end
$upscope $end
$enddefinitions $end
$comment Show the parameter values. $end
$dumpall
b10111110101111000010000000 -
b1010001011000 ,
b10010110000000 +
b1000 *
b10 )
b1 (
$end
#0
$dumpvars
b1 1
b0 0
b1 /
b0 .
b101010100 '
0&
0%
b101010100 $
0#
x"
0!
$end
#5
1#
#10
0#
1&
#15
1#
#20
b10 1
0#
1%
#25
b10 /
1#
#30
0#
#35
0"
b1 0
1#
#40
0#
#45
b10 0
1#
#50
0#
#55
b11 0
1#
#60
0#
#65
b100 0
1#
#70
0#
#75
b101 0
1#
#80
0#
#85
b110 0
1#
#90
0#
#95
b111 0
1#
#100
0#
#105
b1000 0
1#
#110
0#
#115
b1001 0
1#
#120
0#
#125
b1010 0
1#
#130
0#
#135
b1011 0
1#
#140
0#
#145
b1100 0
1#
#150
0#
#155
b1101 0
1#
#160
0#
#165
b1110 0
1#
#170
0#
#175
b1111 0
1#
#180
0#
#185
b10000 0
1#
#190
0#
#195
b10001 0
1#
#200
0#
#205
b10010 0
1#
#210
0#
#215
b10011 0
1#
#220
0#
#225
b10100 0
1#
#230
0#
#235
b10101 0
1#
#240
0#
#245
b10110 0
1#
#250
0#
#255
b10111 0
1#
#260
0#
#265
b11000 0
1#
#270
0#
#275
b11001 0
1#
#280
0#
#285
b11010 0
1#
#290
0#
#295
b11011 0
1#
#300
0#
#305
b11100 0
1#
#310
0#
#315
b11101 0
1#
#320
0#
#325
b11110 0
1#
#330
0#
#335
b11111 0
1#
#340
0#
#345
b100000 0
1#
#350
0#
#355
b100001 0
1#
#360
0#
#365
b100010 0
1#
#370
0#
#375
b100011 0
1#
#380
0#
#385
b100100 0
1#
#390
0#
#395
b100101 0
1#
#400
0#
#405
b100110 0
1#
#410
0#
#415
b100111 0
1#
#420
0#
#425
b101000 0
1#
#430
0#
#435
b101001 0
1#
#440
0#
#445
b101010 0
1#
#450
0#
#455
b101011 0
1#
#460
0#
#465
b101100 0
1#
#470
0#
#475
b101101 0
1#
#480
0#
#485
b101110 0
1#
#490
0#
#495
b101111 0
1#
#500
0#
#505
b110000 0
1#
#510
0#
#515
b110001 0
1#
#520
0#
#525
b110010 0
1#
#530
0#
#535
b110011 0
1#
#540
0#
#545
b110100 0
1#
#550
0#
#555
b110101 0
1#
#560
0#
#565
b110110 0
1#
#570
0#
#575
b110111 0
1#
#580
0#
#585
b111000 0
1#
#590
0#
#595
b111001 0
1#
#600
0#
#605
b111010 0
1#
#610
0#
#615
b111011 0
1#
#620
0#
#625
b111100 0
1#
#630
0#
#635
b111101 0
1#
#640
0#
#645
b111110 0
1#
#650
0#
#655
b111111 0
1#
#660
0#
#665
b1000000 0
1#
#670
0#
#675
b1000001 0
1#
#680
0#
#685
b1000010 0
1#
#690
0#
#695
b1000011 0
1#
#700
0#
#705
b1000100 0
1#
#710
0#
#715
b1000101 0
1#
#720
0#
#725
b1000110 0
1#
#730
0#
#735
b1000111 0
1#
#740
0#
#745
b1001000 0
1#
#750
0#
#755
b1001001 0
1#
#760
0#
#765
b1001010 0
1#
#770
0#
#775
b1001011 0
1#
#780
0#
#785
b1001100 0
1#
#790
0#
#795
b1001101 0
1#
#800
0#
#805
b1001110 0
1#
#810
0#
#815
b1001111 0
1#
#820
0#
#825
b1010000 0
1#
#830
0#
#835
b1010001 0
1#
#840
0#
#845
b1010010 0
1#
#850
0#
#855
b1010011 0
1#
#860
0#
#865
b1010100 0
1#
#870
0#
#875
b1010101 0
1#
#880
0#
#885
b1010110 0
1#
#890
0#
#895
b1010111 0
1#
#900
0#
#905
b1011000 0
1#
#910
0#
#915
b1011001 0
1#
#920
0#
#925
b1011010 0
1#
#930
0#
#935
b1011011 0
1#
#940
0#
#945
b1011100 0
1#
#950
0#
#955
b1011101 0
1#
#960
0#
#965
b1011110 0
1#
#970
0#
#975
b1011111 0
1#
#980
0#
#985
b1100000 0
1#
#990
0#
#995
b1100001 0
1#
#1000
0#
#1005
b1100010 0
1#
#1010
0#
#1015
b1100011 0
1#
#1020
0#
#1025
b1100100 0
1#
#1030
0#
#1035
b1100101 0
1#
#1040
0#
#1045
b1100110 0
1#
#1050
0#
#1055
b1100111 0
1#
#1060
0#
#1065
b1101000 0
1#
#1070
0#
#1075
b1101001 0
1#
#1080
0#
#1085
b1101010 0
1#
#1090
0#
#1095
b1101011 0
1#
#1100
0#
#1105
b1101100 0
1#
#1110
0#
#1115
b1101101 0
1#
#1120
0#
#1125
b1101110 0
1#
#1130
0#
#1135
b1101111 0
1#
#1140
0#
#1145
b1110000 0
1#
#1150
0#
#1155
b1110001 0
1#
#1160
0#
#1165
b1110010 0
1#
#1170
0#
#1175
b1110011 0
1#
#1180
0#
#1185
b1110100 0
1#
#1190
0#
#1195
b1110101 0
1#
#1200
0#
#1205
b1110110 0
1#
#1210
0#
#1215
b1110111 0
1#
#1220
0#
#1225
b1111000 0
1#
#1230
0#
#1235
b1111001 0
1#
#1240
0#
#1245
b1111010 0
1#
#1250
0#
#1255
b1111011 0
1#
#1260
0#
#1265
b1111100 0
1#
#1270
0#
#1275
b1111101 0
1#
#1280
0#
#1285
b1111110 0
1#
#1290
0#
#1295
b1111111 0
1#
#1300
0#
#1305
b10000000 0
1#
#1310
0#
#1315
b10000001 0
1#
#1320
0#
#1325
b10000010 0
1#
#1330
0#
#1335
b10000011 0
1#
#1340
0#
#1345
b10000100 0
1#
#1350
0#
#1355
b10000101 0
1#
#1360
0#
#1365
b10000110 0
1#
#1370
0#
#1375
b10000111 0
1#
#1380
0#
#1385
b10001000 0
1#
#1390
0#
#1395
b10001001 0
1#
#1400
0#
#1405
b10001010 0
1#
#1410
0#
#1415
b10001011 0
1#
#1420
0#
#1425
b10001100 0
1#
#1430
0#
#1435
b10001101 0
1#
#1440
0#
#1445
b10001110 0
1#
#1450
0#
#1455
b10001111 0
1#
#1460
0#
#1465
b10010000 0
1#
#1470
0#
#1475
b10010001 0
1#
#1480
0#
#1485
b10010010 0
1#
#1490
0#
#1495
b10010011 0
1#
#1500
0#
#1505
b10010100 0
1#
#1510
0#
#1515
b10010101 0
1#
#1520
0#
#1525
b10010110 0
1#
#1530
0#
#1535
b10010111 0
1#
#1540
0#
#1545
b10011000 0
1#
#1550
0#
#1555
b10011001 0
1#
#1560
0#
#1565
b10011010 0
1#
#1570
0#
#1575
b10011011 0
1#
#1580
0#
#1585
b10011100 0
1#
#1590
0#
#1595
b10011101 0
1#
#1600
0#
#1605
b10011110 0
1#
#1610
0#
#1615
b10011111 0
1#
#1620
0#
#1625
b10100000 0
1#
#1630
0#
#1635
b10100001 0
1#
#1640
0#
#1645
b10100010 0
1#
#1650
0#
#1655
b10100011 0
1#
#1660
0#
#1665
b10100100 0
1#
#1670
0#
#1675
b10100101 0
1#
#1680
0#
#1685
b10100110 0
1#
#1690
0#
#1695
b10100111 0
1#
#1700
0#
#1705
b10101000 0
1#
#1710
0#
#1715
b10101001 0
1#
#1720
0#
#1725
b10101010 0
1#
#1730
0#
#1735
b10101011 0
1#
#1740
0#
#1745
b10101100 0
1#
#1750
0#
#1755
b10101101 0
1#
#1760
0#
#1765
b10101110 0
1#
#1770
0#
#1775
b10101111 0
1#
#1780
0#
#1785
b10110000 0
1#
#1790
0#
#1795
b10110001 0
1#
#1800
0#
#1805
b10110010 0
1#
#1810
0#
#1815
b10110011 0
1#
#1820
0#
#1825
b10110100 0
1#
#1830
0#
#1835
b10110101 0
1#
#1840
0#
#1845
b10110110 0
1#
#1850
0#
#1855
b10110111 0
1#
#1860
0#
#1865
b10111000 0
1#
#1870
0#
#1875
b10111001 0
1#
#1880
0#
#1885
b10111010 0
1#
#1890
0#
#1895
b10111011 0
1#
#1900
0#
#1905
b10111100 0
1#
#1910
0#
#1915
b10111101 0
1#
#1920
0#
#1925
b10111110 0
1#
#1930
0#
#1935
b10111111 0
1#
#1940
0#
#1945
b11000000 0
1#
#1950
0#
#1955
b11000001 0
1#
#1960
0#
#1965
b11000010 0
1#
#1970
0#
#1975
b11000011 0
1#
#1980
0#
#1985
b11000100 0
1#
#1990
0#
#1995
b11000101 0
1#
#2000
0#
#2005
b11000110 0
1#
#2010
0#
#2015
b11000111 0
1#
#2020
0#
#2025
b11001000 0
1#
#2030
0#
#2035
b11001001 0
1#
#2040
0#
#2045
b11001010 0
1#
#2050
0#
#2055
b11001011 0
1#
#2060
0#
#2065
b11001100 0
1#
#2070
0#
#2075
b11001101 0
1#
#2080
0#
#2085
b11001110 0
1#
#2090
0#
#2095
b11001111 0
1#
#2100
0#
#2105
b11010000 0
1#
#2110
0#
#2115
b11010001 0
1#
#2120
0#
#2125
b11010010 0
1#
#2130
0#
#2135
b11010011 0
1#
#2140
0#
#2145
b11010100 0
1#
#2150
0#
#2155
b11010101 0
1#
#2160
0#
#2165
b11010110 0
1#
#2170
0#
#2175
b11010111 0
1#
#2180
0#
#2185
b11011000 0
1#
#2190
0#
#2195
b11011001 0
1#
#2200
0#
#2205
b11011010 0
1#
#2210
0#
#2215
b11011011 0
1#
#2220
0#
#2225
b11011100 0
1#
#2230
0#
#2235
b11011101 0
1#
#2240
0#
#2245
b11011110 0
1#
#2250
0#
#2255
b11011111 0
1#
#2260
0#
#2265
b11100000 0
1#
#2270
0#
#2275
b11100001 0
1#
#2280
0#
#2285
b11100010 0
1#
#2290
0#
#2295
b11100011 0
1#
#2300
0#
#2305
b11100100 0
1#
#2310
0#
#2315
b11100101 0
1#
#2320
0#
#2325
b11100110 0
1#
#2330
0#
#2335
b11100111 0
1#
#2340
0#
#2345
b11101000 0
1#
#2350
0#
#2355
b11101001 0
1#
#2360
0#
#2365
b11101010 0
1#
#2370
0#
#2375
b11101011 0
1#
#2380
0#
#2385
b11101100 0
1#
#2390
0#
#2395
b11101101 0
1#
#2400
0#
#2405
b11101110 0
1#
#2410
0#
#2415
b11101111 0
1#
#2420
0#
#2425
b11110000 0
1#
#2430
0#
#2435
b11110001 0
1#
#2440
0#
#2445
b11110010 0
1#
#2450
0#
#2455
b11110011 0
1#
#2460
0#
#2465
b11110100 0
1#
#2470
0#
#2475
b11110101 0
1#
#2480
0#
#2485
b11110110 0
1#
#2490
0#
#2495
b11110111 0
1#
#2500
0#
#2505
b11111000 0
1#
#2510
0#
#2515
b11111001 0
1#
#2520
0#
#2525
b11111010 0
1#
#2530
0#
#2535
b11111011 0
1#
#2540
0#
#2545
b11111100 0
1#
#2550
0#
#2555
b11111101 0
1#
#2560
0#
#2565
b11111110 0
1#
#2570
0#
#2575
b11111111 0
1#
#2580
0#
#2585
b100000000 0
1#
#2590
0#
#2595
b100000001 0
1#
#2600
0#
#2605
b100000010 0
1#
#2610
0#
#2615
b100000011 0
1#
#2620
0#
#2625
b100000100 0
1#
#2630
0#
#2635
b100000101 0
1#
#2640
0#
#2645
b100000110 0
1#
#2650
0#
#2655
b100000111 0
1#
#2660
0#
#2665
b100001000 0
1#
#2670
0#
#2675
b100001001 0
1#
#2680
0#
#2685
b100001010 0
1#
#2690
0#
#2695
b100001011 0
1#
#2700
0#
#2705
b100001100 0
1#
#2710
0#
#2715
b100001101 0
1#
#2720
0#
#2725
b100001110 0
1#
#2730
0#
#2735
b100001111 0
1#
#2740
0#
#2745
b100010000 0
1#
#2750
0#
#2755
b100010001 0
1#
#2760
0#
#2765
b100010010 0
1#
#2770
0#
#2775
b100010011 0
1#
#2780
0#
#2785
b100010100 0
1#
#2790
0#
#2795
b100010101 0
1#
#2800
0#
#2805
b100010110 0
1#
#2810
0#
#2815
b100010111 0
1#
#2820
0#
#2825
b100011000 0
1#
#2830
0#
#2835
b100011001 0
1#
#2840
0#
#2845
b100011010 0
1#
#2850
0#
#2855
b100011011 0
1#
#2860
0#
#2865
b100011100 0
1#
#2870
0#
#2875
b100011101 0
1#
#2880
0#
#2885
b100011110 0
1#
#2890
0#
#2895
b100011111 0
1#
#2900
0#
#2905
b100100000 0
1#
#2910
0#
#2915
b100100001 0
1#
#2920
0#
#2925
b100100010 0
1#
#2930
0#
#2935
b100100011 0
1#
#2940
0#
#2945
b100100100 0
1#
#2950
0#
#2955
b100100101 0
1#
#2960
0#
#2965
b100100110 0
1#
#2970
0#
#2975
b100100111 0
1#
#2980
0#
#2985
b100101000 0
1#
#2990
0#
#2995
b100101001 0
1#
#3000
0#
#3005
b100101010 0
1#
#3010
0#
#3015
b100101011 0
1#
#3020
0#
#3025
b100101100 0
1#
#3030
0#
#3035
b100101101 0
1#
#3040
0#
#3045
b100101110 0
1#
#3050
0#
#3055
b100101111 0
1#
#3060
0#
#3065
b100110000 0
1#
#3070
0#
#3075
b100110001 0
1#
#3080
0#
#3085
b100110010 0
1#
#3090
0#
#3095
b100110011 0
1#
#3100
0#
#3105
b100110100 0
1#
#3110
0#
#3115
b100110101 0
1#
#3120
0#
#3125
b100110110 0
1#
#3130
0#
#3135
b100110111 0
1#
#3140
0#
#3145
b100111000 0
1#
#3150
0#
#3155
b100111001 0
1#
#3160
0#
#3165
b100111010 0
1#
#3170
0#
#3175
b100111011 0
1#
#3180
0#
#3185
b100111100 0
1#
#3190
0#
#3195
b100111101 0
1#
#3200
0#
#3205
b100111110 0
1#
#3210
0#
#3215
b100111111 0
1#
#3220
0#
#3225
b101000000 0
1#
#3230
0#
#3235
b101000001 0
1#
#3240
0#
#3245
b101000010 0
1#
#3250
0#
#3255
b101000011 0
1#
#3260
0#
#3265
b101000100 0
1#
#3270
0#
#3275
b101000101 0
1#
#3280
0#
#3285
b101000110 0
1#
#3290
0#
#3295
b101000111 0
1#
#3300
0#
#3305
b101001000 0
1#
#3310
0#
#3315
b101001001 0
1#
#3320
0#
#3325
b101001010 0
1#
#3330
0#
#3335
b101001011 0
1#
#3340
0#
#3345
b101001100 0
1#
#3350
0#
#3355
b101001101 0
1#
#3360
0#
#3365
b101001110 0
1#
#3370
0#
#3375
b101001111 0
1#
#3380
0#
#3385
b101010000 0
1#
#3390
0#
#3395
b101010001 0
1#
#3400
0#
#3405
b101010010 0
1#
#3410
0#
#3415
b101010011 0
1#
#3420
0#
#3425
b101010100 0
1#
#3430
0#
#3435
b101010101 0
1#
#3440
0#
#3445
b101010110 0
1#
#3450
0#
#3455
b101010111 0
1#
#3460
0#
#3465
b101011000 0
1#
#3470
0#
#3475
b101011001 0
1#
#3480
0#
#3485
b101011010 0
1#
#3490
0#
#3495
b101011011 0
1#
#3500
0#
#3505
b101011100 0
1#
#3510
0#
#3515
b101011101 0
1#
#3520
0#
#3525
b101011110 0
1#
#3530
0#
#3535
b101011111 0
1#
#3540
0#
#3545
b101100000 0
1#
#3550
0#
#3555
b101100001 0
1#
#3560
0#
#3565
b101100010 0
1#
#3570
0#
#3575
b101100011 0
1#
#3580
0#
#3585
b101100100 0
1#
#3590
0#
#3595
b101100101 0
1#
#3600
0#
#3605
b101100110 0
1#
#3610
0#
#3615
b101100111 0
1#
#3620
0#
#3625
b101101000 0
1#
#3630
0#
#3635
b101101001 0
1#
#3640
0#
#3645
b101101010 0
1#
#3650
0#
#3655
b101101011 0
1#
#3660
0#
#3665
b101101100 0
1#
#3670
0#
#3675
b101101101 0
1#
#3680
0#
#3685
b101101110 0
1#
#3690
0#
#3695
b101101111 0
1#
#3700
0#
#3705
b101110000 0
1#
#3710
0#
#3715
b101110001 0
1#
#3720
0#
#3725
b101110010 0
1#
#3730
0#
#3735
b101110011 0
1#
#3740
0#
#3745
b101110100 0
1#
#3750
0#
#3755
b101110101 0
1#
#3760
0#
#3765
b101110110 0
1#
#3770
0#
#3775
b101110111 0
1#
#3780
0#
#3785
b101111000 0
1#
#3790
0#
#3795
b101111001 0
1#
#3800
0#
#3805
b101111010 0
1#
#3810
0#
#3815
b101111011 0
1#
#3820
0#
#3825
b101111100 0
1#
#3830
0#
#3835
b101111101 0
1#
#3840
0#
#3845
b101111110 0
1#
#3850
0#
#3855
b101111111 0
1#
#3860
0#
#3865
b110000000 0
1#
#3870
0#
#3875
b110000001 0
1#
#3880
0#
#3885
b110000010 0
1#
#3890
0#
#3895
b110000011 0
1#
#3900
0#
#3905
b110000100 0
1#
#3910
0#
#3915
b110000101 0
1#
#3920
0#
#3925
b110000110 0
1#
#3930
0#
#3935
b110000111 0
1#
#3940
0#
#3945
b110001000 0
1#
#3950
0#
#3955
b110001001 0
1#
#3960
0#
#3965
b110001010 0
1#
#3970
0#
#3975
b110001011 0
1#
#3980
0#
#3985
b110001100 0
1#
#3990
0#
#3995
b110001101 0
1#
#4000
0#
#4005
b110001110 0
1#
#4010
0#
#4015
b110001111 0
1#
#4020
0#
#4025
b110010000 0
1#
#4030
0#
#4035
b110010001 0
1#
#4040
0#
#4045
b110010010 0
1#
#4050
0#
#4055
b110010011 0
1#
#4060
0#
#4065
b110010100 0
1#
#4070
0#
#4075
b110010101 0
1#
#4080
0#
#4085
b110010110 0
1#
#4090
0#
#4095
b110010111 0
1#
#4100
0#
#4105
b110011000 0
1#
#4110
0#
#4115
b110011001 0
1#
#4120
0#
#4125
b110011010 0
1#
#4130
0#
#4135
b110011011 0
1#
#4140
0#
#4145
b110011100 0
1#
#4150
0#
#4155
b110011101 0
1#
#4160
0#
#4165
b110011110 0
1#
#4170
0#
#4175
b110011111 0
1#
#4180
0#
#4185
b110100000 0
1#
#4190
0#
#4195
b110100001 0
1#
#4200
0#
#4205
b110100010 0
1#
#4210
0#
#4215
b110100011 0
1#
#4220
0#
#4225
b110100100 0
1#
#4230
0#
#4235
b110100101 0
1#
#4240
0#
#4245
b110100110 0
1#
#4250
0#
#4255
b110100111 0
1#
#4260
0#
#4265
b110101000 0
1#
#4270
0#
#4275
b110101001 0
1#
#4280
0#
#4285
b110101010 0
1#
#4290
0#
#4295
b110101011 0
1#
#4300
0#
#4305
b110101100 0
1#
#4310
0#
#4315
b110101101 0
1#
#4320
0#
#4325
b110101110 0
1#
#4330
0#
#4335
b110101111 0
1#
#4340
0#
#4345
b110110000 0
1#
#4350
0#
#4355
b110110001 0
1#
#4360
0#
#4365
b110110010 0
1#
#4370
0#
#4375
b110110011 0
1#
#4380
0#
#4385
b110110100 0
1#
#4390
0#
#4395
b110110101 0
1#
#4400
0#
#4405
b110110110 0
1#
#4410
0#
#4415
b110110111 0
1#
#4420
0#
#4425
b110111000 0
1#
#4430
0#
#4435
b110111001 0
1#
#4440
0#
#4445
b110111010 0
1#
#4450
0#
#4455
b110111011 0
1#
#4460
0#
#4465
b110111100 0
1#
#4470
0#
#4475
b110111101 0
1#
#4480
0#
#4485
b110111110 0
1#
#4490
0#
#4495
b110111111 0
1#
#4500
0#
#4505
b111000000 0
1#
#4510
0#
#4515
b111000001 0
1#
#4520
0#
#4525
b111000010 0
1#
#4530
0#
#4535
b111000011 0
1#
#4540
0#
#4545
b111000100 0
1#
#4550
0#
#4555
b111000101 0
1#
#4560
0#
#4565
b111000110 0
1#
#4570
0#
#4575
b111000111 0
1#
#4580
0#
#4585
b111001000 0
1#
#4590
0#
#4595
b111001001 0
1#
#4600
0#
#4605
b111001010 0
1#
#4610
0#
#4615
b111001011 0
1#
#4620
0#
#4625
b111001100 0
1#
#4630
0#
#4635
b111001101 0
1#
#4640
0#
#4645
b111001110 0
1#
#4650
0#
#4655
b111001111 0
1#
#4660
0#
#4665
b111010000 0
1#
#4670
0#
#4675
b111010001 0
1#
#4680
0#
#4685
b111010010 0
1#
#4690
0#
#4695
b111010011 0
1#
#4700
0#
#4705
b111010100 0
1#
#4710
0#
#4715
b111010101 0
1#
#4720
0#
#4725
b111010110 0
1#
#4730
0#
#4735
b111010111 0
1#
#4740
0#
#4745
b111011000 0
1#
#4750
0#
#4755
b111011001 0
1#
#4760
0#
#4765
b111011010 0
1#
#4770
0#
#4775
b111011011 0
1#
#4780
0#
#4785
b111011100 0
1#
#4790
0#
#4795
b111011101 0
1#
#4800
0#
#4805
b111011110 0
1#
#4810
0#
#4815
b111011111 0
1#
#4820
0#
#4825
b111100000 0
1#
#4830
0#
#4835
b111100001 0
1#
#4840
0#
#4845
b111100010 0
1#
#4850
0#
#4855
b111100011 0
1#
#4860
0#
#4865
b111100100 0
1#
#4870
0#
#4875
b111100101 0
1#
#4880
0#
#4885
b111100110 0
1#
#4890
0#
#4895
b111100111 0
1#
#4900
0#
#4905
b111101000 0
1#
#4910
0#
#4915
b111101001 0
1#
#4920
0#
#4925
b111101010 0
1#
#4930
0#
#4935
b111101011 0
1#
#4940
0#
#4945
b111101100 0
1#
#4950
0#
#4955
b111101101 0
1#
#4960
0#
#4965
b111101110 0
1#
#4970
0#
#4975
b111101111 0
1#
#4980
0#
#4985
b111110000 0
1#
#4990
0#
#4995
b111110001 0
1#
#5000
0#
#5005
b111110010 0
1#
#5010
0#
#5015
b111110011 0
1#
#5020
0#
#5025
b111110100 0
1#
#5030
0#
#5035
b111110101 0
1#
#5040
0#
#5045
b111110110 0
1#
#5050
0#
#5055
b111110111 0
1#
#5060
0#
#5065
b111111000 0
1#
#5070
0#
#5075
b111111001 0
1#
#5080
0#
#5085
b111111010 0
1#
#5090
0#
#5095
b111111011 0
1#
#5100
0#
#5105
b111111100 0
1#
#5110
0#
#5115
b111111101 0
1#
#5120
0#
#5125
b111111110 0
1#
#5130
0#
#5135
b111111111 0
1#
#5140
0#
#5145
b1000000000 0
1#
#5150
0#
#5155
b1000000001 0
1#
#5160
0#
#5165
b1000000010 0
1#
#5170
0#
#5175
b1000000011 0
1#
#5180
0#
#5185
b1000000100 0
1#
#5190
0#
#5195
b1000000101 0
1#
#5200
0#
#5205
b1000000110 0
1#
#5210
0#
#5215
b1000000111 0
1#
#5220
0#
#5225
b1000001000 0
1#
#5230
0#
#5235
b1000001001 0
1#
#5240
0#
#5245
b1000001010 0
1#
#5250
0#
#5255
b1000001011 0
1#
#5260
0#
#5265
b1000001100 0
1#
#5270
0#
#5275
b1000001101 0
1#
#5280
0#
#5285
b1000001110 0
1#
#5290
0#
#5295
b1000001111 0
1#
#5300
0#
#5305
b1000010000 0
1#
#5310
0#
#5315
b1000010001 0
1#
#5320
0#
#5325
b1000010010 0
1#
#5330
0#
#5335
b1000010011 0
1#
#5340
0#
#5345
b1000010100 0
1#
#5350
0#
#5355
b1000010101 0
1#
#5360
0#
#5365
b1000010110 0
1#
#5370
0#
#5375
b1000010111 0
1#
#5380
0#
#5385
b1000011000 0
1#
#5390
0#
#5395
b1000011001 0
1#
#5400
0#
#5405
b1000011010 0
1#
#5410
0#
#5415
b1000011011 0
1#
#5420
0#
#5425
b1000011100 0
1#
#5430
0#
#5435
b1000011101 0
1#
#5440
0#
#5445
b1000011110 0
1#
#5450
0#
#5455
b1000011111 0
1#
#5460
0#
#5465
b1000100000 0
1#
#5470
0#
#5475
b1000100001 0
1#
#5480
0#
#5485
b1000100010 0
1#
#5490
0#
#5495
b1000100011 0
1#
#5500
0#
#5505
b1000100100 0
1#
#5510
0#
#5515
b1000100101 0
1#
#5520
0#
#5525
b1000100110 0
1#
#5530
0#
#5535
b1000100111 0
1#
#5540
0#
#5545
b1000101000 0
1#
#5550
0#
#5555
b1000101001 0
1#
#5560
0#
#5565
b1000101010 0
1#
#5570
0#
#5575
b1000101011 0
1#
#5580
0#
#5585
b1000101100 0
1#
#5590
0#
#5595
b1000101101 0
1#
#5600
0#
#5605
b1000101110 0
1#
#5610
0#
#5615
b1000101111 0
1#
#5620
0#
#5625
b1000110000 0
1#
#5630
0#
#5635
b1000110001 0
1#
#5640
0#
#5645
b1000110010 0
1#
#5650
0#
#5655
b1000110011 0
1#
#5660
0#
#5665
b1000110100 0
1#
#5670
0#
#5675
b1000110101 0
1#
#5680
0#
#5685
b1000110110 0
1#
#5690
0#
#5695
b1000110111 0
1#
#5700
0#
#5705
b1000111000 0
1#
#5710
0#
#5715
b1000111001 0
1#
#5720
0#
#5725
b1000111010 0
1#
#5730
0#
#5735
b1000111011 0
1#
#5740
0#
#5745
b1000111100 0
1#
#5750
0#
#5755
b1000111101 0
1#
#5760
0#
#5765
b1000111110 0
1#
#5770
0#
#5775
b1000111111 0
1#
#5780
0#
#5785
b1001000000 0
1#
#5790
0#
#5795
b1001000001 0
1#
#5800
0#
#5805
b1001000010 0
1#
#5810
0#
#5815
b1001000011 0
1#
#5820
0#
#5825
b1001000100 0
1#
#5830
0#
#5835
b1001000101 0
1#
#5840
0#
#5845
b1001000110 0
1#
#5850
0#
#5855
b1001000111 0
1#
#5860
0#
#5865
b1001001000 0
1#
#5870
0#
#5875
b1001001001 0
1#
#5880
0#
#5885
b1001001010 0
1#
#5890
0#
#5895
b1001001011 0
1#
#5900
0#
#5905
b1001001100 0
1#
#5910
0#
#5915
b1001001101 0
1#
#5920
0#
#5925
b1001001110 0
1#
#5930
0#
#5935
b1001001111 0
1#
#5940
0#
#5945
b1001010000 0
1#
#5950
0#
#5955
b1001010001 0
1#
#5960
0#
#5965
b1001010010 0
1#
#5970
0#
#5975
b1001010011 0
1#
#5980
0#
#5985
b1001010100 0
1#
#5990
0#
#5995
b1001010101 0
1#
#6000
0#
#6005
b1001010110 0
1#
#6010
0#
#6015
b1001010111 0
1#
#6020
0#
#6025
b1001011000 0
1#
#6030
0#
#6035
b1001011001 0
1#
#6040
0#
#6045
b1001011010 0
1#
#6050
0#
#6055
b1001011011 0
1#
#6060
0#
#6065
b1001011100 0
1#
#6070
0#
#6075
b1001011101 0
1#
#6080
0#
#6085
b1001011110 0
1#
#6090
0#
#6095
b1001011111 0
1#
#6100
0#
#6105
b1001100000 0
1#
#6110
0#
#6115
b1001100001 0
1#
#6120
0#
#6125
b1001100010 0
1#
#6130
0#
#6135
b1001100011 0
1#
#6140
0#
#6145
b1001100100 0
1#
#6150
0#
#6155
b1001100101 0
1#
#6160
0#
#6165
b1001100110 0
1#
#6170
0#
#6175
b1001100111 0
1#
#6180
0#
#6185
b1001101000 0
1#
#6190
0#
#6195
b1001101001 0
1#
#6200
0#
#6205
b1001101010 0
1#
#6210
0#
#6215
b1001101011 0
1#
#6220
0#
#6225
b1001101100 0
1#
#6230
0#
#6235
b1001101101 0
1#
#6240
0#
#6245
b1001101110 0
1#
#6250
0#
#6255
b1001101111 0
1#
#6260
0#
#6265
b1001110000 0
1#
