learn/SPI/spi.v
//实现spi全擦除 W25Q16 模块


module spi(sys_clk,reset,en_sig,cs,spi_clk,out);
input sys_clk;                      // 系统时钟    50M
input reset;                        // 复位信号
input en_sig;                       // 擦除使能信号

output reg spi_clk;                 // spi时钟    

output reg cs;                      // 片选信号
reg [7:0]Mosi;                      // 主机发送数据
output reg out;
parameter WR_EN_IN = 8'h06;               // 写使能命令
parameter BE_IN  = 8'hC7;                 // 全擦除指令

// status
parameter IDLE = 4'b0001;
parameter WREN = 4'b0010;
parameter DELAY = 4'b0100;
parameter BE = 4'b1000;




reg [2:0] devider_count;               //分频计数器
//产生串行时钟 12.5Mhz 对50Mhz的系统时钟进行4分频
always @(posedge sys_clk or negedge reset) begin
    if(reset == 1'b0) 
        devider_count <= 3'b0;
    else if(devider_count == 3'b11) 
        devider_count <= 1'b0;
    else
        devider_count <= devider_count+ 1'b1;
end

//时钟输出
always @(posedge sys_clk or negedge reset) begin
    if(reset == 1'b0) begin
        spi_clk <= 3'b0;
    end
    else if(devider_count == 3'b10) 
        spi_clk <= 1'b1;
    else
        spi_clk <= 1'b0;
end

reg [2:0] bit_count;               //数据位计数器
reg [3:0] state;                   //状态机状态
reg [2:0] state_count;             //状态计数器
reg [2:0] spi_count;               //spi计数器 没计数8个时钟时候切换一次状态

always@(posedge spi_clk or negedge reset) begin
    if(reset == 1'b0 ) begin
        spi_count <= 3'b0;
    end
    else if(spi_count == 3'b111) begin
        spi_count <= 3'b0;
    end
    else if(en_sig == 1'b1 ) begin
        spi_count <= spi_count + 1'b1;      //使能信号有效时候 状态计数器开始计数
    end
end


always@(posedge spi_clk or negedge reset) begin
    if(reset == 1'b0 ) begin
        state_count <= 3'b0;
    end
    else if( en_sig == 1'b1 && spi_count == 3'b111) begin
        state_count <= state_count + 1'b1;      //使能信号有效时候 状态计数器开始计数
    end
  
end

always@(posedge spi_clk or negedge reset) begin
    if(reset == 1'b0) begin
        state <= IDLE;
    end
    else begin
        case(state)
            IDLE: begin
                if(en_sig == 1'b1 && state_count == 3'b001) begin
                    state <= WREN;
                end
                else begin
                    state <= IDLE;
                end
            end
            WREN: begin
                if(state_count == 3'b100) begin
                    state <= DELAY;
                end
                 
            end
            DELAY: begin
                if(state_count == 3'b110) begin
                    state <= BE;
                end
            end
            BE: begin
                if(state_count == 3'b111) begin
                    state <= IDLE;
                end
            end
        endcase
    end
end

// data sender
always@(posedge spi_clk or negedge reset) begin
    if(reset == 1'b0) begin
        cs <= 1'b1;
        Mosi <= 8'b0;
    end
    else begin
        case(state)
            WREN: begin
                cs <= 1'b0;
                Mosi <= WR_EN_IN;
            end
            BE: begin
                cs <= 1'b0;
                Mosi <= BE_IN;
            end
            default: begin
                cs <= 1'b1;
                Mosi <= 8'b0;
            end
        endcase
    end
end

always@(posedge spi_clk or negedge reset) begin
    if(reset == 1'b0) begin
        out <= 1'b0;
        bit_count <= 3'b0;
    end
    else if(state == WREN ) begin
        out <=  Mosi[7-bit_count];
        bit_count <= bit_count + 1'b1;
    end
    else if(state == BE) begin
        out <=  Mosi[7-bit_count];
        bit_count <= bit_count + 1'b1;
    end
    else begin
        out <= 1'b0;
        bit_count <= 3'b0;
    end
end


endmodule

learn/SPI/spi_tb.v
`timescale 1ns/1ns
module spi_tb;

    reg clk;
    reg rst;
    wire spi_clk;
    reg en_sig;

    wire cs;
    wire out;
    initial begin
        $dumpfile("spi.vcd");
        $dumpvars(0, spi_tb);
    end


    initial 
    begin
        clk = 0;
        rst = 1;
        en_sig = 0;
        # 100 rst = 0;
        # 100 rst = 1;
        # 100 en_sig = 0;
        # 100 en_sig = 1;

        # 4000 $finish;
    end

    always #5 clk = ~clk;

    spi spi_dut(
        .sys_clk(clk),
        .reset(rst),
        .en_sig(en_sig),
        .spi_clk(spi_clk),
        .cs(cs),
        .out(out)
    );

endmodule

learn/SPI/spi.vcd
$date
	Mon Aug 17 17:21:33 2026
$end
$version
	Icarus Verilog
$end
$timescale
	1ns
$end
$scope module spi_tb $end
$var wire 1 ! spi_clk $end
$var wire 1 " out $end
$var wire 1 # cs $end
$var reg 1 $ clk $end
$var reg 1 % en_sig $end
$var reg 1 & rst $end
$scope module spi_dut $end
$var wire 1 % en_sig $end
$var wire 1 & reset $end
$var wire 1 $ sys_clk $end
$var parameter 4 ' BE $end
$var parameter 8 ( BE_IN $end
$var parameter 4 ) DELAY $end
$var parameter 4 * IDLE $end
$var parameter 4 + WREN $end
$var parameter 8 , WR_EN_IN $end
$var reg 8 - Mosi [7:0] $end
$var reg 3 . bit_count [2:0] $end
$var reg 1 # cs $end
$var reg 3 / devider_count [2:0] $end
$var reg 1 " out $end
$var reg 1 ! spi_clk $end
$var reg 3 0 spi_count [2:0] $end
$var reg 4 1 state [3:0] $end
$var reg 3 2 state_count [2:0] $end
$upscope $end
$upscope $end
$enddefinitions $end
$comment Show the parameter values. $end
$dumpall
b11111111 ,
b10 +
b1 *
b100 )
b11111111 (
b1000 '
$end
#0
$dumpvars
bx 2
bx 1
bx 0
bx /
bx .
bx -
1&
0%
0$
x#
x"
x!
$end
#5
0!
1$
#10
0$
#15
1$
#20
0$
#25
1$
#30
0$
#35
1$
#40
0$
#45
1$
#50
0$
#55
1$
#60
0$
#65
1$
#70
0$
#75
1$
#80
0$
#85
1$
#90
0$
#95
1$
#100
b0 0
b0 2
b1 1
b0 -
1#
b0 .
0"
b0 /
0$
0&
#105
1$
#110
0$
#115
1$
#120
0$
#125
1$
#130
0$
#135
1$
#140
0$
#145
1$
#150
0$
#155
1$
#160
0$
#165
1$
#170
0$
#175
1$
#180
0$
#185
1$
#190
0$
#195
1$
#200
0$
1&
#205
b1 /
1$
#210
0$
#215
b10 /
1$
#220
0$
#225
1!
b11 /
1$
#230
0$
#235
b0 /
0!
1$
#240
0$
#245
b1 /
1$
#250
0$
#255
b10 /
1$
#260
0$
#265
1!
b11 /
1$
#270
0$
#275
b0 /
0!
1$
#280
0$
#285
b1 /
1$
#290
0$
#295
b10 /
1$
#300
0$
#305
1!
b11 /
1$
#310
0$
#315
b0 /
0!
1$
#320
0$
#325
b1 /
1$
#330
0$
#335
b10 /
1$
#340
0$
#345
1!
b11 /
1$
#350
0$
#355
b0 /
0!
1$
#360
0$
#365
b1 /
1$
#370
0$
#375
b10 /
1$
#380
0$
#385
1!
b11 /
1$
#390
0$
#395
b0 /
0!
1$
#400
0$
1%
#405
b1 /
1$
#410
0$
#415
b10 /
1$
#420
0$
#425
b1 0
1!
b11 /
1$
#430
0$
#435
b0 /
0!
1$
#440
0$
#445
b1 /
1$
#450
0$
#455
b10 /
1$
#460
0$
#465
b10 0
1!
b11 /
1$
#470
0$
#475
b0 /
0!
1$
#480
0$
#485
b1 /
1$
#490
0$
#495
b10 /
1$
#500
0$
#505
b11 0
1!
b11 /
1$
#510
0$
#515
b0 /
0!
1$
#520
0$
#525
b1 /
1$
#530
0$
#535
b10 /
1$
#540
0$
#545
b100 0
1!
b11 /
1$
#550
0$
#555
b0 /
0!
1$
#560
0$
#565
b1 /
1$
#570
0$
#575
b10 /
1$
#580
0$
#585
b101 0
1!
b11 /
1$
#590
0$
#595
b0 /
0!
1$
#600
0$
#605
b1 /
1$
#610
0$
#615
b10 /
1$
#620
0$
#625
b110 0
1!
b11 /
1$
#630
0$
#635
b0 /
0!
1$
#640
0$
#645
b1 /
1$
#650
0$
#655
b10 /
1$
#660
0$
#665
b111 0
1!
b11 /
1$
#670
0$
#675
b0 /
0!
1$
#680
0$
#685
b1 /
1$
#690
0$
#695
b10 /
1$
#700
0$
#705
b1 2
b0 0
1!
b11 /
1$
#710
0$
#715
b0 /
0!
1$
#720
0$
#725
b1 /
1$
#730
0$
#735
b10 /
1$
#740
0$
#745
b1 0
b10 1
1!
b11 /
1$
#750
0$
#755
b0 /
0!
1$
#760
0$
#765
b1 /
1$
#770
0$
#775
b10 /
1$
#780
0$
#785
b1 .
b11111111 -
0#
b10 0
1!
b11 /
1$
#790
0$
#795
b0 /
0!
1$
#800
0$
#805
b1 /
1$
#810
0$
#815
b10 /
1$
#820
0$
#825
b11 0
b10 .
1"
1!
b11 /
1$
#830
0$
#835
b0 /
0!
1$
#840
0$
#845
b1 /
1$
#850
0$
#855
b10 /
1$
#860
0$
#865
b11 .
b100 0
1!
b11 /
1$
#870
0$
#875
b0 /
0!
1$
#880
0$
#885
b1 /
1$
#890
0$
#895
b10 /
1$
#900
0$
#905
b101 0
b100 .
1!
b11 /
1$
#910
0$
#915
b0 /
0!
1$
#920
0$
#925
b1 /
1$
#930
0$
#935
b10 /
1$
#940
0$
#945
b101 .
b110 0
1!
b11 /
1$
#950
0$
#955
b0 /
0!
1$
#960
0$
#965
b1 /
1$
#970
0$
#975
b10 /
1$
#980
0$
#985
b111 0
b110 .
1!
b11 /
1$
#990
0$
#995
b0 /
0!
1$
#1000
0$
#1005
b1 /
1$
#1010
0$
#1015
b10 /
1$
#1020
0$
#1025
b111 .
b10 2
b0 0
1!
b11 /
1$
#1030
0$
#1035
b0 /
0!
1$
#1040
0$
#1045
b1 /
1$
#1050
0$
#1055
b10 /
1$
#1060
0$
#1065
b1 0
b0 .
1!
b11 /
1$
#1070
0$
#1075
b0 /
0!
1$
#1080
0$
#1085
b1 /
1$
#1090
0$
#1095
b10 /
1$
#1100
0$
#1105
b1 .
b10 0
1!
b11 /
1$
#1110
0$
#1115
b0 /
0!
1$
#1120
0$
#1125
b1 /
1$
#1130
0$
#1135
b10 /
1$
#1140
0$
#1145
b11 0
b10 .
1!
b11 /
1$
#1150
0$
#1155
b0 /
0!
1$
#1160
0$
#1165
b1 /
1$
#1170
0$
#1175
b10 /
1$
#1180
0$
#1185
b11 .
b100 0
1!
b11 /
1$
#1190
0$
#1195
b0 /
0!
1$
#1200
0$
#1205
b1 /
1$
#1210
0$
#1215
b10 /
1$
#1220
0$
#1225
b101 0
b100 .
1!
b11 /
1$
#1230
0$
#1235
b0 /
0!
1$
#1240
0$
#1245
b1 /
1$
#1250
0$
#1255
b10 /
1$
#1260
0$
#1265
b101 .
b110 0
1!
b11 /
1$
#1270
0$
#1275
b0 /
0!
1$
#1280
0$
#1285
b1 /
1$
#1290
0$
#1295
b10 /
1$
#1300
0$
#1305
b111 0
b110 .
1!
b11 /
1$
#1310
0$
#1315
b0 /
0!
1$
#1320
0$
#1325
b1 /
1$
#1330
0$
#1335
b10 /
1$
#1340
0$
#1345
b111 .
b11 2
b0 0
1!
b11 /
1$
#1350
0$
#1355
b0 /
0!
1$
#1360
0$
#1365
b1 /
1$
#1370
0$
#1375
b10 /
1$
#1380
0$
#1385
b1 0
b0 .
1!
b11 /
1$
#1390
0$
#1395
b0 /
0!
1$
#1400
0$
#1405
b1 /
1$
#1410
0$
#1415
b10 /
1$
#1420
0$
#1425
b1 .
b10 0
1!
b11 /
1$
#1430
0$
#1435
b0 /
0!
1$
#1440
0$
#1445
b1 /
1$
#1450
0$
#1455
b10 /
1$
#1460
0$
#1465
b11 0
b10 .
1!
b11 /
1$
#1470
0$
#1475
b0 /
0!
1$
#1480
0$
#1485
b1 /
1$
#1490
0$
#1495
b10 /
1$
#1500
0$
#1505
b11 .
b100 0
1!
b11 /
1$
#1510
0$
#1515
b0 /
0!
1$
#1520
0$
#1525
b1 /
1$
#1530
0$
#1535
b10 /
1$
#1540
0$
#1545
b101 0
b100 .
1!
b11 /
1$
#1550
0$
#1555
b0 /
0!
1$
#1560
0$
#1565
b1 /
1$
#1570
0$
#1575
b10 /
1$
#1580
0$
#1585
b101 .
b110 0
1!
b11 /
1$
#1590
0$
#1595
b0 /
0!
1$
#1600
0$
#1605
b1 /
1$
#1610
0$
#1615
b10 /
1$
#1620
0$
#1625
b111 0
b110 .
1!
b11 /
1$
#1630
0$
#1635
b0 /
0!
1$
#1640
0$
#1645
b1 /
1$
#1650
0$
#1655
b10 /
1$
#1660
0$
#1665
b111 .
b100 2
b0 0
1!
b11 /
1$
#1670
0$
#1675
b0 /
0!
1$
#1680
0$
#1685
b1 /
1$
#1690
0$
#1695
b10 /
1$
#1700
0$
#1705
b1 0
b100 1
b0 .
1!
b11 /
1$
#1710
0$
#1715
b0 /
0!
1$
#1720
0$
#1725
b1 /
1$
#1730
0$
#1735
b10 /
1$
#1740
0$
#1745
0"
b0 -
1#
b10 0
1!
b11 /
1$
#1750
0$
#1755
b0 /
0!
1$
#1760
0$
#1765
b1 /
1$
#1770
0$
#1775
b10 /
1$
#1780
0$
#1785
b11 0
1!
b11 /
1$
#1790
0$
#1795
b0 /
0!
1$
#1800
0$
#1805
b1 /
1$
#1810
0$
#1815
b10 /
1$
#1820
0$
#1825
b100 0
1!
b11 /
1$
#1830
0$
#1835
b0 /
0!
1$
#1840
0$
#1845
b1 /
1$
#1850
0$
#1855
b10 /
1$
#1860
0$
#1865
b101 0
1!
b11 /
1$
#1870
0$
#1875
b0 /
0!
1$
#1880
0$
#1885
b1 /
1$
#1890
0$
#1895
b10 /
1$
#1900
0$
#1905
b110 0
1!
b11 /
1$
#1910
0$
#1915
b0 /
0!
1$
#1920
0$
#1925
b1 /
1$
#1930
0$
#1935
b10 /
1$
#1940
0$
#1945
b111 0
1!
b11 /
1$
#1950
0$
#1955
b0 /
0!
1$
#1960
0$
#1965
b1 /
1$
#1970
0$
#1975
b10 /
1$
#1980
0$
#1985
b101 2
b0 0
1!
b11 /
1$
#1990
0$
#1995
b0 /
0!
1$
#2000
0$
#2005
b1 /
1$
#2010
0$
#2015
b10 /
1$
#2020
0$
#2025
b1 0
1!
b11 /
1$
#2030
0$
#2035
b0 /
0!
1$
#2040
0$
#2045
b1 /
1$
#2050
0$
#2055
b10 /
1$
#2060
0$
#2065
b10 0
1!
b11 /
1$
#2070
0$
#2075
b0 /
0!
1$
#2080
0$
#2085
b1 /
1$
#2090
0$
#2095
b10 /
1$
#2100
0$
#2105
b11 0
1!
b11 /
1$
#2110
0$
#2115
b0 /
0!
1$
#2120
0$
#2125
b1 /
1$
#2130
0$
#2135
b10 /
1$
#2140
0$
#2145
b100 0
1!
b11 /
1$
#2150
0$
#2155
b0 /
0!
1$
#2160
0$
#2165
b1 /
1$
#2170
0$
#2175
b10 /
1$
#2180
0$
#2185
b101 0
1!
b11 /
1$
#2190
0$
#2195
b0 /
0!
1$
#2200
0$
#2205
b1 /
1$
#2210
0$
#2215
b10 /
1$
#2220
0$
#2225
b110 0
1!
b11 /
1$
#2230
0$
#2235
b0 /
0!
1$
#2240
0$
#2245
b1 /
1$
#2250
0$
#2255
b10 /
1$
#2260
0$
#2265
b111 0
1!
b11 /
1$
#2270
0$
#2275
b0 /
0!
1$
#2280
0$
#2285
b1 /
1$
#2290
0$
#2295
b10 /
1$
#2300
0$
#2305
b110 2
b0 0
1!
b11 /
1$
#2310
0$
#2315
b0 /
0!
1$
#2320
0$
#2325
b1 /
1$
#2330
0$
#2335
b10 /
1$
#2340
0$
#2345
b1 0
b1000 1
1!
b11 /
1$
#2350
0$
#2355
b0 /
0!
1$
#2360
0$
#2365
b1 /
1$
#2370
0$
#2375
b10 /
1$
#2380
0$
#2385
b1 .
b11111111 -
0#
b10 0
1!
b11 /
1$
#2390
0$
#2395
b0 /
0!
1$
#2400
0$
#2405
b1 /
1$
#2410
0$
#2415
b10 /
1$
#2420
0$
#2425
b11 0
b10 .
1"
1!
b11 /
1$
#2430
0$
#2435
b0 /
0!
1$
#2440
0$
#2445
b1 /
1$
#2450
0$
#2455
b10 /
1$
#2460
0$
#2465
b11 .
b100 0
1!
b11 /
1$
#2470
0$
#2475
b0 /
0!
1$
#2480
0$
#2485
b1 /
1$
#2490
0$
#2495
b10 /
1$
#2500
0$
#2505
b101 0
b100 .
1!
b11 /
1$
#2510
0$
#2515
b0 /
0!
1$
#2520
0$
#2525
b1 /
1$
#2530
0$
#2535
b10 /
1$
#2540
0$
#2545
b101 .
b110 0
1!
b11 /
1$
#2550
0$
#2555
b0 /
0!
1$
#2560
0$
#2565
b1 /
1$
#2570
0$
#2575
b10 /
1$
#2580
0$
#2585
b111 0
b110 .
1!
b11 /
1$
#2590
0$
#2595
b0 /
0!
1$
#2600
0$
#2605
b1 /
1$
#2610
0$
#2615
b10 /
1$
#2620
0$
#2625
b111 .
b111 2
b0 0
1!
b11 /
1$
#2630
0$
#2635
b0 /
0!
1$
#2640
0$
#2645
b1 /
1$
#2650
0$
#2655
b10 /
1$
#2660
0$
#2665
b1 0
b1 1
b0 .
1!
b11 /
1$
#2670
0$
#2675
b0 /
0!
1$
#2680
0$
#2685
b1 /
1$
#2690
0$
#2695
b10 /
1$
#2700
0$
#2705
0"
b0 -
1#
b10 0
1!
b11 /
1$
#2710
0$
#2715
b0 /
0!
1$
#2720
0$
#2725
b1 /
1$
#2730
0$
#2735
b10 /
1$
#2740
0$
#2745
b11 0
1!
b11 /
1$
#2750
0$
#2755
b0 /
0!
1$
#2760
0$
#2765
b1 /
1$
#2770
0$
#2775
b10 /
1$
#2780
0$
#2785
b100 0
1!
b11 /
1$
#2790
0$
#2795
b0 /
0!
1$
#2800
0$
#2805
b1 /
1$
#2810
0$
#2815
b10 /
1$
#2820
0$
#2825
b101 0
1!
b11 /
1$
#2830
0$
#2835
b0 /
0!
1$
#2840
0$
#2845
b1 /
1$
#2850
0$
#2855
b10 /
1$
#2860
0$
#2865
b110 0
1!
b11 /
1$
#2870
0$
#2875
b0 /
0!
1$
#2880
0$
#2885
b1 /
1$
#2890
0$
#2895
b10 /
1$
#2900
0$
#2905
b111 0
1!
b11 /
1$
#2910
0$
#2915
b0 /
0!
1$
#2920
0$
#2925
b1 /
1$
#2930
0$
#2935
b10 /
1$
#2940
0$
#2945
b0 2
b0 0
1!
b11 /
1$
#2950
0$
#2955
b0 /
0!
1$
#2960
0$
#2965
b1 /
1$
#2970
0$
#2975
b10 /
1$
#2980
0$
#2985
b1 0
1!
b11 /
1$
#2990
0$
#2995
b0 /
0!
1$
#3000
0$
#3005
b1 /
1$
#3010
0$
#3015
b10 /
1$
#3020
0$
#3025
b10 0
1!
b11 /
1$
#3030
0$
#3035
b0 /
0!
1$
#3040
0$
#3045
b1 /
1$
#3050
0$
#3055
b10 /
1$
#3060
0$
#3065
b11 0
1!
b11 /
1$
#3070
0$
#3075
b0 /
0!
1$
#3080
0$
#3085
b1 /
1$
#3090
0$
#3095
b10 /
1$
#3100
0$
#3105
b100 0
1!
b11 /
1$
#3110
0$
#3115
b0 /
0!
1$
#3120
0$
#3125
b1 /
1$
#3130
0$
#3135
b10 /
1$
#3140
0$
#3145
b101 0
1!
b11 /
1$
#3150
0$
#3155
b0 /
0!
1$
#3160
0$
#3165
b1 /
1$
#3170
0$
#3175
b10 /
1$
#3180
0$
#3185
b110 0
1!
b11 /
1$
#3190
0$
#3195
b0 /
0!
1$
#3200
0$
#3205
b1 /
1$
#3210
0$
#3215
b10 /
1$
#3220
0$
#3225
b111 0
1!
b11 /
1$
#3230
0$
#3235
b0 /
0!
1$
#3240
0$
#3245
b1 /
1$
#3250
0$
#3255
b10 /
1$
#3260
0$
#3265
b1 2
b0 0
1!
b11 /
1$
#3270
0$
#3275
b0 /
0!
1$
#3280
0$
#3285
b1 /
1$
#3290
0$
#3295
b10 /
1$
#3300
0$
#3305
b1 0
b10 1
1!
b11 /
1$
#3310
0$
#3315
b0 /
0!
1$
#3320
0$
#3325
b1 /
1$
#3330
0$
#3335
b10 /
1$
#3340
0$
#3345
b1 .
b11111111 -
0#
b10 0
1!
b11 /
1$
#3350
0$
#3355
b0 /
0!
1$
#3360
0$
#3365
b1 /
1$
#3370
0$
#3375
b10 /
1$
#3380
0$
#3385
b11 0
b10 .
1"
1!
b11 /
1$
#3390
0$
#3395
b0 /
0!
1$
#3400
0$
#3405
b1 /
1$
#3410
0$
#3415
b10 /
1$
#3420
0$
#3425
b11 .
b100 0
1!
b11 /
1$
#3430
0$
#3435
b0 /
0!
1$
#3440
0$
#3445
b1 /
1$
#3450
0$
#3455
b10 /
1$
#3460
0$
#3465
b101 0
b100 .
1!
b11 /
1$
#3470
0$
#3475
b0 /
0!
1$
#3480
0$
#3485
b1 /
1$
#3490
0$
#3495
b10 /
1$
#3500
0$
#3505
b101 .
b110 0
1!
b11 /
1$
#3510
0$
#3515
b0 /
0!
1$
#3520
0$
#3525
b1 /
1$
#3530
0$
#3535
b10 /
1$
#3540
0$
#3545
b111 0
b110 .
1!
b11 /
1$
#3550
0$
#3555
b0 /
0!
1$
#3560
0$
#3565
b1 /
1$
#3570
0$
#3575
b10 /
1$
#3580
0$
#3585
b111 .
b10 2
b0 0
1!
b11 /
1$
#3590
0$
#3595
b0 /
0!
1$
#3600
0$
#3605
b1 /
1$
#3610
0$
#3615
b10 /
1$
#3620
0$
#3625
b1 0
b0 .
1!
b11 /
1$
#3630
0$
#3635
b0 /
0!
1$
#3640
0$
#3645
b1 /
1$
#3650
0$
#3655
b10 /
1$
#3660
0$
#3665
b1 .
b10 0
1!
b11 /
1$
#3670
0$
#3675
b0 /
0!
1$
#3680
0$
#3685
b1 /
1$
#3690
0$
#3695
b10 /
1$
#3700
0$
#3705
b11 0
b10 .
1!
b11 /
1$
#3710
0$
#3715
b0 /
0!
1$
#3720
0$
#3725
b1 /
1$
#3730
0$
#3735
b10 /
1$
#3740
0$
#3745
b11 .
b100 0
1!
b11 /
1$
#3750
0$
#3755
b0 /
0!
1$
#3760
0$
#3765
b1 /
1$
#3770
0$
#3775
b10 /
1$
#3780
0$
#3785
b101 0
b100 .
1!
b11 /
1$
#3790
0$
#3795
b0 /
0!
1$
#3800
0$
#3805
b1 /
1$
#3810
0$
#3815
b10 /
1$
#3820
0$
#3825
b101 .
b110 0
1!
b11 /
1$
#3830
0$
#3835
b0 /
0!
1$
#3840
0$
#3845
b1 /
1$
#3850
0$
#3855
b10 /
1$
#3860
0$
#3865
b111 0
b110 .
1!
b11 /
1$
#3870
0$
#3875
b0 /
0!
1$
#3880
0$
#3885
b1 /
1$
#3890
0$
#3895
b10 /
1$
#3900
0$
#3905
b111 .
b11 2
b0 0
1!
b11 /
1$
#3910
0$
#3915
b0 /
0!
1$
#3920
0$
#3925
b1 /
1$
#3930
0$
#3935
b10 /
1$
#3940
0$
#3945
b1 0
b0 .
1!
b11 /
1$
#3950
0$
#3955
b0 /
0!
1$
#3960
0$
#3965
b1 /
1$
#3970
0$
#3975
b10 /
1$
#3980
0$
#3985
b1 .
b10 0
1!
b11 /
1$
#3990
0$
#3995
b0 /
0!
1$
#4000
0$
#4005
b1 /
1$
#4010
0$
#4015
b10 /
1$
#4020
0$
#4025
b11 0
b10 .
1!
b11 /
1$
#4030
0$
#4035
b0 /
0!
1$
#4040
0$
#4045
b1 /
1$
#4050
0$
#4055
b10 /
1$
#4060
0$
#4065
b11 .
b100 0
1!
b11 /
1$
#4070
0$
#4075
b0 /
0!
1$
#4080
0$
#4085
b1 /
1$
#4090
0$
#4095
b10 /
1$
#4100
0$
#4105
b101 0
b100 .
1!
b11 /
1$
#4110
0$
#4115
b0 /
0!
1$
#4120
0$
#4125
b1 /
1$
#4130
0$
#4135
b10 /
1$
#4140
0$
#4145
b101 .
b110 0
1!
b11 /
1$
#4150
0$
#4155
b0 /
0!
1$
#4160
0$
#4165
b1 /
1$
#4170
0$
#4175
b10 /
1$
#4180
0$
#4185
b111 0
b110 .
1!
b11 /
1$
#4190
0$
#4195
b0 /
0!
1$
#4200
0$
#4205
b1 /
1$
#4210
0$
#4215
b10 /
1$
#4220
0$
#4225
b111 .
b100 2
b0 0
1!
b11 /
1$
#4230
0$
#4235
b0 /
0!
1$
#4240
0$
#4245
b1 /
1$
#4250
0$
#4255
b10 /
1$
#4260
0$
#4265
b1 0
b100 1
b0 .
1!
b11 /
1$
#4270
0$
#4275
b0 /
0!
1$
#4280
0$
#4285
b1 /
1$
#4290
0$
#4295
b10 /
1$
#4300
0$
#4305
0"
b0 -
1#
b10 0
1!
b11 /
1$
#4310
0$
#4315
b0 /
0!
1$
#4320
0$
#4325
b1 /
1$
#4330
0$
#4335
b10 /
1$
#4340
0$
#4345
b11 0
1!
b11 /
1$
#4350
0$
#4355
b0 /
0!
1$
#4360
0$
#4365
b1 /
1$
#4370
0$
#4375
b10 /
1$
#4380
0$
#4385
b100 0
1!
b11 /
1$
#4390
0$
#4395
b0 /
0!
1$
