learn/8sel1/Eight_Sel_One.v
module Eight_Sel_One(data, sel, y);

input [7:0] data;
input [2:0] sel;
output reg y;
always@(*) begin
    case(sel) 
        3'b000: y = data[0];
        3'b001: y = data[1];
        3'b010: y = data[2];
        3'b011: y = data[3];
        3'b100: y = data[4];
        3'b101: y = data[5];
        3'b110: y = data[6];
        3'b111: y = data[7];
    endcase
end

endmodule

learn/8sel1/Eight_Sel_One_tb.v
`timescale 10ns/1ns
// `include "Eight_Sel_One.v"
module Eight_Sel_One_tb();


reg [7:0] a;
reg [2:0] s;
wire y;
Eight_Sel_One dut(.data(a),.sel(s),.y(y));
initial begin
    $dumpfile("wave.vcd");  // 波形文件名
    $dumpvars(0, Eight_Sel_One_tb);  // 记录当前模块所有信号
end

initial begin
	a = 8'b10101010;
	s = 3'b000;
	# 100;
	s = 3'b001;
	# 100;
	s = 3'b010;
	# 100;
	s = 3'b011;
	# 100;
	s = 3'b100;
	# 100;
	s = 3'b101;
	# 100;
	s = 3'b110;
	# 100;
	s = 3'b111;
	# 100;
	$finish;
end





endmodule

learn/8sel1/wave.vcd
$date
	Wed Aug 12 09:54:29 2026
$end
$version
	Icarus Verilog
$end
$timescale
	1ns
$end
$scope module Eight_Sel_One_tb $end
$var wire 1 ! y $end
$var reg 8 " a [7:0] $end
$var reg 3 # s [2:0] $end
$scope module dut $end
$var wire 8 $ data [7:0] $end
$var wire 3 % sel [2:0] $end
$var reg 1 ! y $end
$upscope $end
$upscope $end
$enddefinitions $end
$comment Show the parameter values. $end
$dumpall
$end
#0
$dumpvars
b0 %
b10101010 $
b0 #
b10101010 "
0!
$end
#1000
1!
b1 #
b1 %
#2000
0!
b10 #
b10 %
#3000
1!
b11 #
b11 %
#4000
0!
b100 #
b100 %
#5000
1!
b101 #
b101 %
#6000
0!
b110 #
b110 %
#7000
1!
b111 #
b111 %
