learn/FSM_manipulate/SPI.v
module SPI(
    input  wire sys_clk,
    input  wire reset_n,
    input  wire en_sig,
    output reg  spi_clk,    // 修改：增加 spi_clk 输出，便于外接从机
    output reg  cs,
    output reg  out
);

// 状态定义
localparam [1:0] IDLE    = 2'b00;
localparam [1:0] PREPAR  = 2'b01;
localparam [1:0] SEND    = 2'b10;
localparam [1:0] RELEASE = 2'b11;

// 待发送数据（可改为输入端口）
parameter [7:0] data = 8'b10101010;

// 内部信号
reg [1:0] current_status;
reg [1:0] next_status;
reg [3:0] count;
reg [7:0] shift_reg;     // 修改：使用移位寄存器代替 bit_count

//========================================================================
// 1. spi_clk 生成
// 修改：仅在 SEND 状态翻转，非 SEND 状态保持低电平
//========================================================================
always @(posedge sys_clk or negedge reset_n) begin
    if (!reset_n) begin
        spi_clk <= 1'b0;
    end else if (current_status == SEND) begin
        spi_clk <= ~spi_clk;
    end else begin
        spi_clk <= 1'b0;
    end
end

//========================================================================
// 2. 计数器
// 修改：状态切换时清零，使用 current_status != next_status 检测
//========================================================================
always @(posedge sys_clk or negedge reset_n) begin
    if (!reset_n) begin
        count <= 4'd0;
    end else if (current_status != next_status) begin
        count <= 4'd0;          // 状态即将切换，清零
    end else if (count == 4'd15) begin
        count <= 4'd0;
    end else begin
        count <= count + 1'd1;
    end
end

//========================================================================
// 3. 状态机时序逻辑
//========================================================================
always @(posedge sys_clk or negedge reset_n) begin
    if (!reset_n) begin
        current_status <= IDLE;
    end else begin
        current_status <= next_status;
    end
end

//========================================================================
// 4. 状态机组合逻辑
//========================================================================
always @(*) begin
    case (current_status)
        IDLE:    next_status = en_sig ? PREPAR : IDLE;
        PREPAR:  next_status = (count == 4'd15) ? SEND : PREPAR;
        SEND:    next_status = (count == 4'd15) ? RELEASE : SEND;
        RELEASE: next_status = (count == 4'd15) ? IDLE : RELEASE;
        default: next_status = IDLE;
    endcase
end

//========================================================================
// 5. 输出逻辑（cs、out、移位寄存器）
// 修改：使用移位寄存器，在 spi_clk 下降沿更新数据，保证上升沿采样稳定
//========================================================================
always @(posedge sys_clk or negedge reset_n) begin
    if (!reset_n) begin
        cs        <= 1'b1;
        out       <= 1'b0;
        shift_reg <= 8'b0;
    end else begin
        case (current_status)
            IDLE: begin
                cs        <= 1'b1;
                out       <= 1'b0;
                shift_reg <= data;      // 预加载待发送数据
            end
            PREPAR: begin
                cs        <= 1'b0;
                out       <= data[7];   // 第一位在第一个spi_clk上升沿前稳定
                shift_reg <= data;
            end
            SEND: begin
                cs <= 1'b0;
                // 当 spi_clk 为高（即将下降）时移位，数据在下降沿更新
                if (spi_clk == 1'b1) begin
                    out       <= shift_reg[6];              // 输出下一位
                    shift_reg <= {shift_reg[6:0], 1'b0};    // 左移
                end
            end
            RELEASE: begin
                cs        <= 1'b0;
                out       <= 1'b0;
                shift_reg <= shift_reg;  // 保持不变
            end
            default: begin
                cs        <= 1'b1;
                out       <= 1'b0;
                shift_reg <= 8'b0;
            end
        endcase
    end
end

endmodule

learn/FSM_manipulate/SPI_tb.v
`timescale 1ns/1ns

module SPI_tb();
reg clk;
reg rst;
reg en;
wire spi_clk;
wire cs;
wire out;

SPI dut(clk, rst, en, spi_clk, cs, out);
initial begin
	$dumpfile("SPI.vcd");
	$dumpvars(0,SPI_tb);
end

initial begin
	clk = 0;
	rst = 0;
	
	#10 rst = 1;
	en = 1;
    # 1000 $finish;
end
always #5 clk = ~clk;
endmodule

learn/FSM_manipulate/SPI.vcd
$date
	Tue Aug 18 17:10:25 2026
$end
$version
	Icarus Verilog
$end
$timescale
	1ns
$end
$scope module SPI_tb $end
$var wire 1 ! spi_clk $end
$var wire 1 " out $end
$var wire 1 # cs $end
$var reg 1 $ clk $end
$var reg 1 % en $end
$var reg 1 & rst $end
$scope module dut $end
$var wire 1 % en_sig $end
$var wire 1 & reset_n $end
$var wire 1 $ sys_clk $end
$var parameter 2 ' IDLE $end
$var parameter 2 ( PREPAR $end
$var parameter 2 ) RELEASE $end
$var parameter 2 * SEND $end
$var parameter 8 + data $end
$var reg 4 , count [3:0] $end
$var reg 1 # cs $end
$var reg 2 - current_status [1:0] $end
$var reg 2 . next_status [1:0] $end
$var reg 1 " out $end
$var reg 8 / shift_reg [7:0] $end
$var reg 1 ! spi_clk $end
$upscope $end
$upscope $end
$enddefinitions $end
$comment Show the parameter values. $end
$dumpall
b10101010 +
b10 *
b11 )
b1 (
b0 '
$end
#0
$dumpvars
b0 /
b0x .
b0 -
b0 ,
0&
x%
0$
1#
0"
0!
$end
#5
1$
#10
b1 .
0$
1%
1&
#15
b1 -
b10101010 /
1$
#20
0$
#25
1"
0#
b1 ,
1$
#30
0$
#35
b10 ,
1$
#40
0$
#45
b11 ,
1$
#50
0$
#55
b100 ,
1$
#60
0$
#65
b101 ,
1$
#70
0$
#75
b110 ,
1$
#80
0$
#85
b111 ,
1$
#90
0$
#95
b1000 ,
1$
#100
0$
#105
b1001 ,
1$
#110
0$
#115
b1010 ,
1$
#120
0$
#125
b1011 ,
1$
#130
0$
#135
b1100 ,
1$
#140
0$
#145
b1101 ,
1$
#150
0$
#155
b1110 ,
1$
#160
0$
#165
b10 .
b1111 ,
1$
#170
0$
#175
b0 ,
b10 -
1$
#180
0$
#185
b1 ,
1!
1$
#190
0$
#195
0!
b10 ,
b1010100 /
0"
1$
#200
0$
#205
b11 ,
1!
1$
#210
0$
#215
0!
b100 ,
b10101000 /
1"
1$
#220
0$
#225
b101 ,
1!
1$
#230
0$
#235
0!
b110 ,
b1010000 /
0"
1$
#240
0$
#245
b111 ,
1!
1$
#250
0$
#255
0!
b1000 ,
b10100000 /
1"
1$
#260
0$
#265
b1001 ,
1!
1$
#270
0$
#275
0!
b1010 ,
b1000000 /
0"
1$
#280
0$
#285
b1011 ,
1!
1$
#290
0$
#295
0!
b1100 ,
b10000000 /
1"
1$
#300
0$
#305
b1101 ,
1!
1$
#310
0$
#315
0!
b1110 ,
b0 /
0"
1$
#320
0$
#325
b11 .
b1111 ,
1!
1$
#330
0$
#335
0!
b0 ,
b11 -
1$
#340
0$
#345
b1 ,
1$
#350
0$
#355
b10 ,
1$
#360
0$
#365
b11 ,
1$
#370
0$
#375
b100 ,
1$
#380
0$
#385
b101 ,
1$
#390
0$
#395
b110 ,
1$
#400
0$
#405
b111 ,
1$
#410
0$
#415
b1000 ,
1$
#420
0$
#425
b1001 ,
1$
#430
0$
#435
b1010 ,
1$
#440
0$
#445
b1011 ,
1$
#450
0$
#455
b1100 ,
1$
#460
0$
#465
b1101 ,
1$
#470
0$
#475
b1110 ,
1$
#480
0$
#485
b0 .
b1111 ,
1$
#490
0$
#495
b1 .
b0 ,
b0 -
1$
#500
0$
#505
b10101010 /
1#
b1 -
1$
#510
0$
#515
b1 ,
1"
0#
1$
#520
0$
#525
b10 ,
1$
#530
0$
#535
b11 ,
1$
#540
0$
#545
b100 ,
1$
#550
0$
#555
b101 ,
1$
#560
0$
#565
b110 ,
1$
#570
0$
#575
b111 ,
1$
#580
0$
#585
b1000 ,
1$
#590
0$
#595
b1001 ,
1$
#600
0$
#605
b1010 ,
1$
#610
0$
#615
b1011 ,
1$
#620
0$
#625
b1100 ,
1$
#630
0$
#635
b1101 ,
1$
#640
0$
#645
b1110 ,
1$
#650
0$
#655
b10 .
b1111 ,
1$
#660
0$
#665
b10 -
b0 ,
1$
#670
0$
#675
1!
b1 ,
1$
#680
0$
#685
b1010100 /
0"
b10 ,
0!
1$
#690
0$
#695
1!
b11 ,
1$
#700
0$
#705
b10101000 /
1"
b100 ,
0!
1$
#710
0$
#715
1!
b101 ,
1$
#720
0$
#725
b1010000 /
0"
b110 ,
0!
1$
#730
0$
#735
1!
b111 ,
1$
#740
0$
#745
b10100000 /
1"
b1000 ,
0!
1$
#750
0$
#755
1!
b1001 ,
1$
#760
0$
#765
b1000000 /
0"
b1010 ,
0!
1$
#770
0$
#775
1!
b1011 ,
1$
#780
0$
#785
b10000000 /
1"
b1100 ,
0!
1$
#790
0$
#795
1!
b1101 ,
1$
#800
0$
#805
b0 /
0"
b1110 ,
0!
1$
#810
0$
#815
b11 .
1!
b1111 ,
1$
#820
0$
#825
b11 -
b0 ,
0!
1$
#830
0$
#835
b1 ,
1$
#840
0$
#845
b10 ,
1$
#850
0$
#855
b11 ,
1$
#860
0$
#865
b100 ,
1$
#870
0$
#875
b101 ,
1$
#880
0$
#885
b110 ,
1$
#890
0$
#895
b111 ,
1$
#900
0$
#905
b1000 ,
1$
#910
0$
#915
b1001 ,
1$
#920
0$
#925
b1010 ,
1$
#930
0$
#935
b1011 ,
1$
#940
0$
#945
b1100 ,
1$
#950
0$
#955
b1101 ,
1$
#960
0$
#965
b1110 ,
1$
#970
0$
#975
b0 .
b1111 ,
1$
#980
0$
#985
b1 .
b0 -
b0 ,
1$
#990
0$
#995
b1 -
b10101010 /
1#
1$
#1000
0$
#1005
1"
0#
b1 ,
1$
