learn/4devider/Four_devider.v
// module Four_devider(clk,rst,clk_out);
//     input clk,rst;
//     output reg clk_out;
//     reg [1:0] count;
//     always@(posedge clk or posedge rst)
//     begin
//         if(rst == 1'b1) begin
//             count <= 2'b00;
//             clk_out <= 1'b0;
//         end
//         else if(count == 2'b01) begin
//             count <= 2'b00;
//         end
//         else
//             count <= count + 1'b1;
//     end

//    always@(posedge clk or posedge rst) begin
//       if(rst == 1'b1)
//        clk_out <= 1'b0;
//       else if(count == 2'b01)
//         clk_out <= ~clk_out;
//       else
//         clk_out <= clk_out;
//     end
    

//     // always@(posedge clk or posedge rst) begin
//     //   if(rst == 1'b1)
//     //    clk_out <= 1'b0;
//     //   else if(count == 2'b01)
//     //     clk_out <= 1'b1;
//     //   else
//     //     clk_out <= 1'b0;
//     // end
// endmodule

module Four_devider(clk,rst,clk_out);
    input clk,rst;
    output reg clk_out;
    reg [1:0] count;
    always@(posedge clk or posedge rst)
    begin
        if(rst == 1'b1) begin
            count <= 2'b00;
            clk_out <= 1'b0;
        end
        else if(count == 2'b11) begin
            count <= 2'b00;
        end
        else
            count <= count + 1'b1;
    end

   always@(posedge clk or posedge rst) begin
      if(rst == 1'b1)
       clk_out <= 1'b0;
      else if(count == 2'b01)
        clk_out <= 1'b1;
      else
        clk_out <= 1'b0;
    end
    


endmodule

learn/4devider/Four_devider_tb.v
`timescale 1ns/1ns
// `include "Four_devider.v"
module Four_devider_tb();

reg clk,rst;
wire out;
Four_devider dut(clk,rst,out);
initial begin
    $dumpfile("Four_devider_tb.vcd");
    $dumpvars(0,dut);
end

initial begin
    clk = 0;
	rst = 1;
    # 10 rst = 0;
    # 500 $finish;
end
always #1 clk = ~clk;
endmodule

learn/4devider/Four_devider_tb.vcd
$date
	Sat Aug 15 09:12:45 2026
$end
$version
	Icarus Verilog
$end
$timescale
	1ns
$end
$scope module Four_devider_tb $end
$scope module dut $end
$var wire 1 ! clk $end
$var wire 1 " rst $end
$var reg 1 # clk_out $end
$var reg 2 $ count [1:0] $end
$upscope $end
$upscope $end
$enddefinitions $end
$comment Show the parameter values. $end
$dumpall
$end
#0
$dumpvars
b0 $
0#
1"
0!
$end
#1
1!
#2
0!
#3
1!
#4
0!
#5
1!
#6
0!
#7
1!
#8
0!
#9
1!
#10
0!
0"
#11
b1 $
1!
#12
0!
#13
1#
b10 $
1!
#14
0!
#15
b11 $
0#
1!
#16
0!
#17
b0 $
1!
#18
0!
#19
b1 $
1!
#20
0!
#21
1#
b10 $
1!
#22
0!
#23
b11 $
0#
1!
#24
0!
#25
b0 $
1!
#26
0!
#27
b1 $
1!
#28
0!
#29
1#
b10 $
1!
#30
0!
#31
b11 $
0#
1!
#32
0!
#33
b0 $
1!
#34
0!
#35
b1 $
1!
#36
0!
#37
1#
b10 $
1!
#38
0!
#39
b11 $
0#
1!
#40
0!
#41
b0 $
1!
#42
0!
#43
b1 $
1!
#44
0!
#45
1#
b10 $
1!
#46
0!
#47
b11 $
0#
1!
#48
0!
#49
b0 $
1!
#50
0!
#51
b1 $
1!
#52
0!
#53
1#
b10 $
1!
#54
0!
#55
b11 $
0#
1!
#56
0!
#57
b0 $
1!
#58
0!
#59
b1 $
1!
#60
0!
#61
1#
b10 $
1!
#62
0!
#63
b11 $
0#
1!
#64
0!
#65
b0 $
1!
#66
0!
#67
b1 $
1!
#68
0!
#69
1#
b10 $
1!
#70
0!
#71
b11 $
0#
1!
#72
0!
#73
b0 $
1!
#74
0!
#75
b1 $
1!
#76
0!
#77
1#
b10 $
1!
#78
0!
#79
b11 $
0#
1!
#80
0!
#81
b0 $
1!
#82
0!
#83
b1 $
1!
#84
0!
#85
1#
b10 $
1!
#86
0!
#87
b11 $
0#
1!
#88
0!
#89
b0 $
1!
#90
0!
#91
b1 $
1!
#92
0!
#93
1#
b10 $
1!
#94
0!
#95
b11 $
0#
1!
#96
0!
#97
b0 $
1!
#98
0!
#99
b1 $
1!
#100
0!
#101
1#
b10 $
1!
#102
0!
#103
b11 $
0#
1!
#104
0!
#105
b0 $
1!
#106
0!
#107
b1 $
1!
#108
0!
#109
1#
b10 $
1!
#110
0!
#111
b11 $
0#
1!
#112
0!
#113
b0 $
1!
#114
0!
#115
b1 $
1!
#116
0!
#117
1#
b10 $
1!
#118
0!
#119
b11 $
0#
1!
#120
0!
#121
b0 $
1!
#122
0!
#123
b1 $
1!
#124
0!
#125
1#
b10 $
1!
#126
0!
#127
b11 $
0#
1!
#128
0!
#129
b0 $
1!
#130
0!
#131
b1 $
1!
#132
0!
#133
1#
b10 $
1!
#134
0!
#135
b11 $
0#
1!
#136
0!
#137
b0 $
1!
#138
0!
#139
b1 $
1!
#140
0!
#141
1#
b10 $
1!
#142
0!
#143
b11 $
0#
1!
#144
0!
#145
b0 $
1!
#146
0!
#147
b1 $
1!
#148
0!
#149
1#
b10 $
1!
#150
0!
#151
b11 $
0#
1!
#152
0!
#153
b0 $
1!
#154
0!
#155
b1 $
1!
#156
0!
#157
1#
b10 $
1!
#158
0!
#159
b11 $
0#
1!
#160
0!
#161
b0 $
1!
#162
0!
#163
b1 $
1!
#164
0!
#165
1#
b10 $
1!
#166
0!
#167
b11 $
0#
1!
#168
0!
#169
b0 $
1!
#170
0!
#171
b1 $
1!
#172
0!
#173
1#
b10 $
1!
#174
0!
#175
b11 $
0#
1!
#176
0!
#177
b0 $
1!
#178
0!
#179
b1 $
1!
#180
0!
#181
1#
b10 $
1!
#182
0!
#183
b11 $
0#
1!
#184
0!
#185
b0 $
1!
#186
0!
#187
b1 $
1!
#188
0!
#189
1#
b10 $
1!
#190
0!
#191
b11 $
0#
1!
#192
0!
#193
b0 $
1!
#194
0!
#195
b1 $
1!
#196
0!
#197
1#
b10 $
1!
#198
0!
#199
b11 $
0#
1!
#200
0!
#201
b0 $
1!
#202
0!
#203
b1 $
1!
#204
0!
#205
1#
b10 $
1!
#206
0!
#207
b11 $
0#
1!
#208
0!
#209
b0 $
1!
#210
0!
#211
b1 $
1!
#212
0!
#213
1#
b10 $
1!
#214
0!
#215
b11 $
0#
1!
#216
0!
#217
b0 $
1!
#218
0!
#219
b1 $
1!
#220
0!
#221
1#
b10 $
1!
#222
0!
#223
b11 $
0#
1!
#224
0!
#225
b0 $
1!
#226
0!
#227
b1 $
1!
#228
0!
#229
1#
b10 $
1!
#230
0!
#231
b11 $
0#
1!
#232
0!
#233
b0 $
1!
#234
0!
#235
b1 $
1!
#236
0!
#237
1#
b10 $
1!
#238
0!
#239
b11 $
0#
1!
#240
0!
#241
b0 $
1!
#242
0!
#243
b1 $
1!
#244
0!
#245
1#
b10 $
1!
#246
0!
#247
b11 $
0#
1!
#248
0!
#249
b0 $
1!
#250
0!
#251
b1 $
1!
#252
0!
#253
1#
b10 $
1!
#254
0!
#255
b11 $
0#
1!
#256
0!
#257
b0 $
1!
#258
0!
#259
b1 $
1!
#260
0!
#261
1#
b10 $
1!
#262
0!
#263
b11 $
0#
1!
#264
0!
#265
b0 $
1!
#266
0!
#267
b1 $
1!
#268
0!
#269
1#
b10 $
1!
#270
0!
#271
b11 $
0#
1!
#272
0!
#273
b0 $
1!
#274
0!
#275
b1 $
1!
#276
0!
#277
1#
b10 $
1!
#278
0!
#279
b11 $
0#
1!
#280
0!
#281
b0 $
1!
#282
0!
#283
b1 $
1!
#284
0!
#285
1#
b10 $
1!
#286
0!
#287
b11 $
0#
1!
#288
0!
#289
b0 $
1!
#290
0!
#291
b1 $
1!
#292
0!
#293
1#
b10 $
1!
#294
0!
#295
b11 $
0#
1!
#296
0!
#297
b0 $
1!
#298
0!
#299
b1 $
1!
#300
0!
#301
1#
b10 $
1!
#302
0!
#303
b11 $
0#
1!
#304
0!
#305
b0 $
1!
#306
0!
#307
b1 $
1!
#308
0!
#309
1#
b10 $
1!
#310
0!
#311
b11 $
0#
1!
#312
0!
#313
b0 $
1!
#314
0!
#315
b1 $
1!
#316
0!
#317
1#
b10 $
1!
#318
0!
#319
b11 $
0#
1!
#320
0!
#321
b0 $
1!
#322
0!
#323
b1 $
1!
#324
0!
#325
1#
b10 $
1!
#326
0!
#327
b11 $
0#
1!
#328
0!
#329
b0 $
1!
#330
0!
#331
b1 $
1!
#332
0!
#333
1#
b10 $
1!
#334
0!
#335
b11 $
0#
1!
#336
0!
#337
b0 $
1!
#338
0!
#339
b1 $
1!
#340
0!
#341
1#
b10 $
1!
#342
0!
#343
b11 $
0#
1!
#344
0!
#345
b0 $
1!
#346
0!
#347
b1 $
1!
#348
0!
#349
1#
b10 $
1!
#350
0!
#351
b11 $
0#
1!
#352
0!
#353
b0 $
1!
#354
0!
#355
b1 $
1!
#356
0!
#357
1#
b10 $
1!
#358
0!
#359
b11 $
0#
1!
#360
0!
#361
b0 $
1!
#362
0!
#363
b1 $
1!
#364
0!
#365
1#
b10 $
1!
#366
0!
#367
b11 $
0#
1!
#368
0!
#369
b0 $
1!
#370
0!
#371
b1 $
1!
#372
0!
#373
1#
b10 $
1!
#374
0!
#375
b11 $
0#
1!
#376
0!
#377
b0 $
1!
#378
0!
#379
b1 $
1!
#380
0!
#381
1#
b10 $
1!
#382
0!
#383
b11 $
0#
1!
#384
0!
#385
b0 $
1!
#386
0!
#387
b1 $
1!
#388
0!
#389
1#
b10 $
1!
#390
0!
#391
b11 $
0#
1!
#392
0!
#393
b0 $
1!
#394
0!
#395
b1 $
1!
#396
0!
#397
1#
b10 $
1!
#398
0!
#399
b11 $
0#
1!
#400
0!
#401
b0 $
1!
#402
0!
#403
b1 $
1!
#404
0!
#405
1#
b10 $
1!
#406
0!
#407
b11 $
0#
1!
#408
0!
#409
b0 $
1!
#410
0!
#411
b1 $
1!
#412
0!
#413
1#
b10 $
1!
#414
0!
#415
b11 $
0#
1!
#416
0!
#417
b0 $
1!
#418
0!
#419
b1 $
1!
#420
0!
#421
1#
b10 $
1!
#422
0!
#423
b11 $
0#
1!
#424
0!
#425
b0 $
1!
#426
0!
#427
b1 $
1!
#428
0!
#429
1#
b10 $
1!
#430
0!
#431
b11 $
0#
1!
#432
0!
#433
b0 $
1!
#434
0!
#435
b1 $
1!
#436
0!
#437
1#
b10 $
1!
#438
0!
#439
b11 $
0#
1!
#440
0!
#441
b0 $
1!
#442
0!
#443
b1 $
1!
#444
0!
#445
1#
b10 $
1!
#446
0!
#447
b11 $
0#
1!
#448
0!
#449
b0 $
1!
#450
0!
#451
b1 $
1!
#452
0!
#453
1#
b10 $
1!
#454
0!
#455
b11 $
0#
1!
#456
0!
#457
b0 $
1!
#458
0!
#459
b1 $
1!
#460
0!
#461
1#
b10 $
1!
#462
0!
#463
b11 $
0#
1!
#464
0!
#465
b0 $
1!
#466
0!
#467
b1 $
1!
#468
0!
#469
1#
b10 $
1!
#470
0!
#471
b11 $
0#
1!
#472
0!
#473
b0 $
1!
#474
0!
#475
b1 $
1!
#476
0!
#477
1#
b10 $
1!
#478
0!
#479
b11 $
0#
1!
#480
0!
#481
b0 $
1!
#482
0!
#483
b1 $
1!
#484
0!
#485
1#
b10 $
1!
#486
0!
#487
b11 $
0#
1!
#488
0!
#489
b0 $
1!
#490
0!
#491
b1 $
1!
#492
0!
#493
1#
b10 $
1!
#494
0!
#495
b11 $
0#
1!
#496
0!
#497
b0 $
1!
#498
0!
#499
b1 $
1!
#500
0!
#501
1#
b10 $
1!
#502
0!
#503
b11 $
0#
1!
#504
0!
#505
b0 $
1!
#506
0!
#507
b1 $
1!
#508
0!
#509
1#
b10 $
1!
