learn/SPI_M/spi_clk.v
module spi_clk(
    input sys_clk,
    input reset_n,
    output reg spi_clk
);
reg [1:0] counter;

always@(posedge sys_clk or negedge reset_n) begin
    if(reset_n == 0)
        spi_clk <= 0;
    else if(counter == 2'b11)
        spi_clk <= 1;
    else
        spi_clk <= 0;
end

always@(posedge sys_clk or negedge reset_n) begin
    if(reset_n == 0)
        counter <= 2'b00;
    else if(counter == 2'b11)
        counter <= 2'b00;
    else
        counter <= counter + 1'b1;
end


endmodule;

learn/SPI_M/spi_clk_tb.v
`timescale 1ns / 1ns
module spi_clk_tb;

reg clk;
reg rest;
wire spi_clk;

spi_clk dut(
	.sys_clk(clk),
	.reset_n(rest),
	.spi_clk(spi_clk)
);

initial begin
	$dumpfile("spi_clk_tb.vcd");
	$dumpvars(0, spi_clk_tb);
end

always #5 clk = ~clk;
initial begin
	clk = 0;
	rest = 0;
	# 100;
	rest = 1;
    # 1000;
    $finish;
end
endmodule

learn/SPI_M/spi_clk_tb.vcd
$date
	Thu Sep 10 14:58:24 2026
$end
$version
	Icarus Verilog
$end
$timescale
	1ns
$end
$scope module spi_clk_tb $end
$var wire 1 ! spi_clk $end
$var reg 1 " clk $end
$var reg 1 # rest $end
$scope module dut $end
$var wire 1 # reset_n $end
$var wire 1 " sys_clk $end
$var reg 2 $ counter [1:0] $end
$var reg 1 ! spi_clk $end
$upscope $end
$upscope $end
$enddefinitions $end
$comment Show the parameter values. $end
$dumpall
$end
#0
$dumpvars
b0 $
0#
0"
0!
$end
#5
1"
#10
0"
#15
1"
#20
0"
#25
1"
#30
0"
#35
1"
#40
0"
#45
1"
#50
0"
#55
1"
#60
0"
#65
1"
#70
0"
#75
1"
#80
0"
#85
1"
#90
0"
#95
1"
#100
0"
1#
#105
b1 $
1"
#110
0"
#115
b10 $
1"
#120
0"
#125
b11 $
1"
#130
0"
#135
1!
b0 $
1"
#140
0"
#145
b1 $
0!
1"
#150
0"
#155
b10 $
1"
#160
0"
#165
b11 $
1"
#170
0"
#175
1!
b0 $
1"
#180
0"
#185
b1 $
0!
1"
#190
0"
#195
b10 $
1"
#200
0"
#205
b11 $
1"
#210
0"
#215
1!
b0 $
1"
#220
0"
#225
b1 $
0!
1"
#230
0"
#235
b10 $
1"
#240
0"
#245
b11 $
1"
#250
0"
#255
1!
b0 $
1"
#260
0"
#265
b1 $
0!
1"
#270
0"
#275
b10 $
1"
#280
0"
#285
b11 $
1"
#290
0"
#295
1!
b0 $
1"
#300
0"
#305
b1 $
0!
1"
#310
0"
#315
b10 $
1"
#320
0"
#325
b11 $
1"
#330
0"
#335
1!
b0 $
1"
#340
0"
#345
b1 $
0!
1"
#350
0"
#355
b10 $
1"
#360
0"
#365
b11 $
1"
#370
0"
#375
1!
b0 $
1"
#380
0"
#385
b1 $
0!
1"
#390
0"
#395
b10 $
1"
#400
0"
#405
b11 $
1"
#410
0"
#415
1!
b0 $
1"
#420
0"
#425
b1 $
0!
1"
#430
0"
#435
b10 $
1"
#440
0"
#445
b11 $
1"
#450
0"
#455
1!
b0 $
1"
#460
0"
#465
b1 $
0!
1"
#470
0"
#475
b10 $
1"
#480
0"
#485
b11 $
1"
#490
0"
#495
1!
b0 $
1"
#500
0"
#505
b1 $
0!
1"
#510
0"
#515
b10 $
1"
#520
0"
#525
b11 $
1"
#530
0"
#535
1!
b0 $
1"
#540
0"
#545
b1 $
0!
1"
#550
0"
#555
b10 $
1"
#560
0"
#565
b11 $
1"
#570
0"
#575
1!
b0 $
1"
#580
0"
#585
b1 $
0!
1"
#590
0"
#595
b10 $
1"
#600
0"
#605
b11 $
1"
#610
0"
#615
1!
b0 $
1"
#620
0"
#625
b1 $
0!
1"
#630
0"
#635
b10 $
1"
#640
0"
#645
b11 $
1"
#650
0"
#655
1!
b0 $
1"
#660
0"
#665
b1 $
0!
1"
#670
0"
#675
b10 $
1"
#680
0"
#685
b11 $
1"
#690
0"
#695
1!
b0 $
1"
#700
0"
#705
b1 $
0!
1"
#710
0"
#715
b10 $
1"
#720
0"
#725
b11 $
1"
#730
0"
#735
1!
b0 $
1"
#740
0"
#745
b1 $
0!
1"
#750
0"
#755
b10 $
1"
#760
0"
#765
b11 $
1"
#770
0"
#775
1!
b0 $
1"
#780
0"
#785
b1 $
0!
1"
#790
0"
#795
b10 $
1"
#800
0"
#805
b11 $
1"
#810
0"
#815
1!
b0 $
1"
#820
0"
#825
b1 $
0!
1"
#830
0"
#835
b10 $
1"
#840
0"
#845
b11 $
1"
#850
0"
#855
1!
b0 $
1"
#860
0"
#865
b1 $
0!
1"
#870
0"
#875
b10 $
1"
#880
0"
#885
b11 $
1"
#890
0"
#895
1!
b0 $
1"
#900
0"
#905
b1 $
0!
1"
#910
0"
#915
b10 $
1"
#920
0"
#925
b11 $
1"
#930
0"
#935
1!
b0 $
1"
#940
0"
#945
b1 $
0!
1"
#950
0"
#955
b10 $
1"
#960
0"
#965
b11 $
1"
#970
0"
#975
1!
b0 $
1"
#980
0"
#985
b1 $
0!
1"
#990
0"
#995
b10 $
1"
#1000
0"
#1005
b11 $
1"
#1010
0"
#1015
1!
b0 $
1"
#1020
0"
#1025
b1 $
0!
1"
#1030
0"
#1035
b10 $
1"
#1040
0"
#1045
b11 $
1"
#1050
0"
#1055
1!
b0 $
1"
#1060
0"
#1065
b1 $
0!
1"
#1070
0"
#1075
b10 $
1"
#1080
0"
#1085
b11 $
1"
#1090
0"
#1095
1!
b0 $
1"
